vhdl/lab02/sr.vhd
library ieee;
use ieee.std_logic_1164.all;
use ieee.numeric_std_unsigned.all;


entity sr is
  generic(
    n : positive := 16
  );
  port(
    clk     : in  std_ulogic;
    sresetn : in  std_ulogic;
    shift   : in  std_ulogic;
    din     : in  std_ulogic;
    dout    : out std_ulogic_vector(n-1 downto 0)
  );
end entity sr;

architecture rtl of sr is
  begin
  process(clk)
  begin
    if rising_edge(clk) then
      if not sresetn then
        dout <= (others => '0');
      else
        if shift then
          dout <= dout(n-2 downto 0) & din;
        end if;
      end if;
    end if;
  end process;
end architecture rtl;

vhdl/lab05/edge.vhd
library ieee;
use ieee.std_logic_1164.all;
use ieee.numeric_std_unsigned.all;

entity edge is
  port(
    clk : in std_ulogic;
    sresetn : in std_ulogic;
    data_in : in std_ulogic;
    re : out std_ulogic;
    fe : out std_ulogic
  );
end entity edge;

architecture rtl of edge is

  signal tmp : std_ulogic_vector(2 downto 0);

begin

  sr3: entity work.sr(rtl)
  
    generic map(n => 3)
  
    port map(
    clk => clk,
    sresetn => sresetn,
    shift => '1',
    din => data_in,
    dout => tmp
    );

    re <= (not tmp(2)) and (tmp(1));
    fe <= (tmp(2)) and (not tmp(1));

end architecture rtl;

vhdl/lab05/edge_sim.vhd
-- MASTER-ONLY: DO NOT MODIFY THIS FILE
--
-- Copyright (C) Telecom Paris
-- Copyright (C) Renaud Pacalet (renaud.pacalet@telecom-paris.fr)
-- 
-- This file must be used under the terms of the CeCILL. This source
-- file is licensed as described in the file COPYING, which you should
-- have received as part of this distribution. The terms are also
-- available at:
-- http://www.cecill.info/licences/Licence_CeCILL_V1.1-US.txt
--

entity edge_sim is
    generic(
        n: positive := 1000 -- duration of test in clock cycles
    );
end entity edge_sim;

use std.env.all;

library ieee;
use ieee.std_logic_1164.all;

library common;
use common.rnd_pkg.all;

architecture sim of edge_sim is

    signal clk:      std_ulogic;
    signal sresetn:  std_ulogic;
    signal data_in:  std_ulogic;
    signal re:       std_ulogic;
    signal fe:       std_ulogic;

    constant clock_period: time := 2 ns;

begin

    edge0: entity work.edge(rtl)
    port map(
        clk     => clk,
        sresetn => sresetn,
        data_in => data_in,
        re      => re,
        fe      => fe
    );

    process
    begin
        clk <= '0';
        wait for clock_period / 2;
        clk <= '1';
        wait for clock_period / 2;
    end process;

    process
        variable r: rnd_generator;
    begin
        sresetn <= '0';
        data_in <= '0';
        for i in 1 to 10 loop
            wait until rising_edge(clk);
        end loop;
        sresetn <= '1';
        for i in 1 to n loop
            if r.get_integer(1, 10) = 1 then
                sresetn <= '0';
            else
                sresetn <= '1';
            end if;
            wait for (0.25 + r.get_real / 2.0) * clock_period;
            data_in <= r.get_std_ulogic;
            wait until rising_edge(clk);
        end loop;
        finish;
    end process;

end architecture sim;

-- vim: set tabstop=4 softtabstop=4 shiftwidth=4 expandtab textwidth=0:

sim/edge_sim.vcd
$date
  Tue Mar 22 14:34:50 2022
$end
$version
  GHDL v0
$end
$timescale
  1 fs
$end
$scope module standard $end
$upscope $end
$scope module env $end
$upscope $end
$scope module textio $end
$upscope $end
$scope module std_logic_1164 $end
$upscope $end
$scope module rnd_pkg $end
$upscope $end
$scope module math_real $end
$upscope $end
$scope module numeric_std_unsigned $end
$upscope $end
$scope module numeric_std $end
$upscope $end
$scope module edge_sim $end
$var reg 1 ! clk $end
$var reg 1 " sresetn $end
$var reg 1 # data_in $end
$var reg 1 $ re $end
$var reg 1 % fe $end
$scope module edge0 $end
$var reg 1 & clk $end
$var reg 1 ' sresetn $end
$var reg 1 ( data_in $end
$var reg 1 ) re $end
$var reg 1 * fe $end
$var reg 3 + tmp[2:0] $end
$scope module sr3 $end
$var reg 1 , clk $end
$var reg 1 - sresetn $end
$var reg 1 . shift $end
$var reg 1 / din $end
$var reg 3 0 dout[2:0] $end
$upscope $end
$upscope $end
$upscope $end
$enddefinitions $end
#0
0!
0"
0#
U$
U%
0&
0'
0(
U)
U*
bUUU +
0,
0-
1.
0/
bUUU 0
#1000000
1!
0$
0%
1&
0)
0*
b000 +
1,
b000 0
#2000000
0!
0&
0,
#3000000
1!
1&
1,
#4000000
0!
0&
0,
#5000000
1!
1&
1,
#6000000
0!
0&
0,
#7000000
1!
1&
1,
#8000000
0!
0&
0,
#9000000
1!
1&
1,
#10000000
0!
0&
0,
#11000000
1!
1&
1,
#12000000
0!
0&
0,
#13000000
1!
1&
1,
#14000000
0!
0&
0,
#15000000
1!
1&
1,
#16000000
0!
0&
0,
#17000000
1!
1&
1,
#18000000
0!
0&
0,
#19000000
1!
1"
1&
1'
1,
1-
#20000000
0!
0&
0,
#20474520
1#
1(
1/
#21000000
1!
1&
b001 +
1,
b001 0
#21536945
0#
0(
0/
#22000000
0!
0&
0,
#23000000
1!
1$
1&
1)
b010 +
1,
b010 0
#23584673
#24000000
0!
0&
0,
#25000000
1!
0$
1%
1&
0)
1*
b100 +
1,
b100 0
#26000000
0!
0&
0,
#26154957
#27000000
1!
0%
1&
0*
b000 +
1,
b000 0
#27611716
#28000000
0!
0&
0,
#29000000
1!
1&
1,
#30000000
0!
0&
0,
#30199824
1#
1(
1/
#31000000
1!
0"
1&
0'
b001 +
1,
0-
b001 0
#32000000
0!
0&
0,
#32402341
#33000000
1!
1"
1&
1'
b000 +
1,
1-
b000 0
#33941179
0#
0(
0/
#34000000
0!
0&
0,
#35000000
1!
1&
1,
#35588210
1#
1(
1/
#36000000
0!
0&
0,
#37000000
1!
1&
b001 +
1,
b001 0
#37647708
#38000000
0!
0&
0,
#39000000
1!
0"
1$
1&
0'
1)
b011 +
1,
0-
b011 0
#39721750
#40000000
0!
0&
0,
#41000000
1!
1"
0$
1&
1'
0)
b000 +
1,
1-
b000 0
#41505257
0#
0(
0/
#42000000
0!
0&
0,
#43000000
1!
1&
1,
#43840707
#44000000
0!
0&
0,
#45000000
1!
1&
1,
#45660774
1#
1(
1/
#46000000
0!
0&
0,
#47000000
1!
0"
1&
0'
b001 +
1,
0-
b001 0
#47914229
0#
0(
0/
#48000000
0!
0&
0,
#49000000
1!
1"
1&
1'
b000 +
1,
1-
b000 0
#49790495
#50000000
0!
0&
0,
#51000000
1!
1&
1,
#52000000
0!
0&
0,
#52291247
#53000000
1!
1&
1,
#53777926
1#
1(
1/
#54000000
0!
0&
0,
#55000000
1!
1&
b001 +
1,
b001 0
#56000000
0!
0&
0,
#56237011
0#
0(
0/
#57000000
1!
1$
1&
1)
b010 +
1,
b010 0
#57863276
#58000000
0!
0&
0,
#59000000
1!
0$
1%
1&
0)
1*
b100 +
1,
b100 0
#60000000
0!
0&
0,
#60029305
1#
1(
1/
#61000000
1!
0%
1&
0*
b001 +
1,
b001 0
#62000000
0!
0&
0,
#62305843
0#
0(
0/
#63000000
1!
1$
1&
1)
b010 +
1,
b010 0
#64000000
0!
0&
0,
#64482377
1#
1(
1/
#65000000
1!
0$
1%
1&
0)
1*
b101 +
1,
b101 0
#65823717
#66000000
0!
0&
0,
#67000000
1!
1$
0%
1&
1)
0*
b011 +
1,
b011 0
#68000000
0!
0&
0,
#68039120
0#
0(
0/
#69000000
1!
0$
1&
0)
b110 +
1,
b110 0
#69876485
1#
1(
1/
#70000000
0!
0&
0,
#71000000
1!
1%
1&
1*
b101 +
1,
b101 0
#71690316
#72000000
0!
0&
0,
#73000000
1!
1$
0%
1&
1)
0*
b011 +
1,
b011 0
#73797185
0#
0(
0/
#74000000
0!
0&
0,
#75000000
1!
0$
1&
0)
b110 +
1,
b110 0
#75828700
#76000000
0!
0&
0,
#77000000
1!
0"
1%
1&
0'
1*
b100 +
1,
0-
b100 0
#77528742
#78000000
0!
0&
0,
#79000000
1!
1"
0%
1&
1'
0*
b000 +
1,
1-
b000 0
#80000000
0!
0&
0,
#80182884
#81000000
1!
1&
1,
#81573544
#82000000
0!
0&
0,
#83000000
1!
1&
1,
#83935129
1#
1(
1/
#84000000
0!
0&
0,
#85000000
1!
1&
b001 +
1,
b001 0
#86000000
0!
0&
0,
#86307372
0#
0(
0/
#87000000
1!
1$
1&
1)
b010 +
1,
b010 0
#88000000
0!
0&
0,
#88022219
#89000000
1!
0$
1%
1&
0)
1*
b100 +
1,
b100 0
#89525128
#90000000
0!
0&
0,
#91000000
1!
0%
1&
0*
b000 +
1,
b000 0
#91522225
#92000000
0!
0&
0,
#93000000
1!
1&
1,
#94000000
0!
0&
0,
#94262306
1#
1(
1/
#95000000
1!
0"
1&
0'
b001 +
1,
0-
b001 0
#96000000
0!
0&
0,
#96279879
0#
0(
0/
#97000000
1!
1"
1&
1'
b000 +
1,
1-
b000 0
#98000000
0!
0&
0,
#98243466
1#
1(
1/
#99000000
1!
1&
b001 +
1,
b001 0
#99633180
#100000000
0!
0&
0,
#101000000
1!
1$
1&
1)
b011 +
1,
b011 0
#101869968
#102000000
0!
0&
0,
#103000000
1!
0$
1&
0)
b111 +
1,
b111 0
#103793273
#104000000
0!
0&
0,
#105000000
1!
1&
1,
#106000000
0!
0&
0,
#106121093
#107000000
1!
1&
1,
#107537575
#108000000
0!
0&
0,
#109000000
1!
1&
1,
#110000000
0!
0&
0,
#110298506
0#
0(
0/
#111000000
1!
1&
b110 +
1,
b110 0
#111763358
#112000000
0!
0&
0,
#113000000
1!
1%
1&
1*
b100 +
1,
b100 0
#113522089
#114000000
0!
0&
0,
#115000000
1!
0%
1&
0*
b000 +
1,
b000 0
#116000000
0!
0&
0,
#116317968
#117000000
1!
1&
1,
#118000000
0!
0&
0,
#118345264
#119000000
1!
1&
1,
#120000000
0!
0&
0,
#120123073
#121000000
1!
1&
1,
#121517779
#122000000
0!
0&
0,
#123000000
1!
1&
1,
#124000000
0!
0&
0,
#124445947
1#
1(
1/
#125000000
1!
1&
b001 +
1,
b001 0
#126000000
0!
0&
0,
#126395006
#127000000
1!
1$
1&
1)
b011 +
1,
b011 0
#128000000
0!
0&
0,
#128290832
#129000000
1!
0$
1&
0)
b111 +
1,
b111 0
#130000000
0!
0&
0,
#130479650
0#
0(
0/
#131000000
1!
1&
b110 +
1,
b110 0
#131558946
#132000000
0!
0&
0,
#133000000
1!
1%
1&
1*
b100 +
1,
b100 0
#133724888
1#
1(
1/
#134000000
0!
0&
0,
#135000000
1!
0%
1&
0*
b001 +
1,
b001 0
#135885107
#136000000
0!
0&
0,
#137000000
1!
1$
1&
1)
b011 +
1,
b011 0
#137588970
#138000000
0!
0&
0,
#139000000
1!
0"
0$
1&
0'
0)
b111 +
1,
0-
b111 0
#139634155
0#
0(
0/
#140000000
0!
0&
0,
#141000000
1!
1"
1&
1'
b000 +
1,
1-
b000 0
#142000000
0!
0&
0,
#142121296
#143000000
1!
1&
1,
#143956883
#144000000
0!
0&
0,
#145000000
1!
0"
1&
0'
1,
0-
#146000000
0!
0&
0,
#146169513
1#
1(
1/
#147000000
1!
1"
1&
1'
1,
1-
#147881877
0#
0(
0/
#148000000
0!
0&
0,
#149000000
1!
1&
1,
#149760912
#150000000
0!
0&
0,
#151000000
1!
0"
1&
0'
1,
0-
#152000000
0!
0&
0,
#152291926
#153000000
1!
1"
1&
1'
1,
1-
#154000000
0!
0&
0,
#154160870
#155000000
1!
1&
1,
#155996220
#156000000
0!
0&
0,
#157000000
1!
1&
1,
#158000000
0!
0&
0,
#158184814
#159000000
1!
1&
1,
#160000000
0!
0&
0,
#160368055
1#
1(
1/
#161000000
1!
1&
b001 +
1,
b001 0
#162000000
0!
0&
0,
#162259322
0#
0(
0/
#163000000
1!
1$
1&
1)
b010 +
1,
b010 0
#164000000
0!
0&
0,
#164341535
1#
1(
1/
#165000000
1!
0$
1%
1&
0)
1*
b101 +
1,
b101 0
#166000000
0!
0&
0,
#166083148
0#
0(
0/
#167000000
1!
1$
0%
1&
1)
0*
b010 +
1,
b010 0
#167955387
1#
1(
1/
#168000000
0!
0&
0,
#169000000
1!
0$
1%
1&
0)
1*
b101 +
1,
b101 0
#170000000
0!
0&
0,
#170297161
0#
0(
0/
#171000000
1!
1$
0%
1&
1)
0*
b010 +
1,
b010 0
#172000000
0!
0&
0,
#172045771
1#
1(
1/
#173000000
1!
0$
1%
1&
0)
1*
b101 +
1,
b101 0
#174000000
0!
0&
0,
#174207093
#175000000
1!
1$
0%
1&
1)
0*
b011 +
1,
b011 0
#176000000
0!
0&
0,
#176170225
0#
0(
0/
#177000000
1!
0$
1&
0)
b110 +
1,
b110 0
#178000000
0!
0&
0,
#178427205
#179000000
1!
0"
1%
1&
0'
1*
b100 +
1,
0-
b100 0
#179687930
1#
1(
1/
#180000000
0!
0&
0,
#181000000
1!
1"
0%
1&
1'
0*
b000 +
1,
1-
b000 0
#182000000
0!
0&
0,
#182057602
0#
0(
0/
#183000000
1!
1&
1,
#183566318
1#
1(
1/
#184000000
0!
0&
0,
#185000000
1!
1&
b001 +
1,
b001 0
#186000000
0!
0&
0,
#186036877
#187000000
1!
1$
1&
1)
b011 +
1,
b011 0
#187930574
0#
0(
0/
#188000000
0!
0&
0,
#189000000
1!
0$
1&
0)
b110 +
1,
b110 0
#189798872
1#
1(
1/
#190000000
0!
0&
0,
#191000000
1!
1%
1&
1*
b101 +
1,
b101 0
#191930187
#192000000
0!
0&
0,
#193000000
1!
1$
0%
1&
1)
0*
b011 +
1,
b011 0
#193910872
0#
0(
0/
#194000000
0!
0&
0,
#195000000
1!
0$
1&
0)
b110 +
1,
b110 0
#195943163
#196000000
0!
0&
0,
#197000000
1!
1%
1&
1*
b100 +
1,
b100 0
#198000000
0!
0&
0,
#198496212
1#
1(
1/
#199000000
1!
0"
0%
1&
0'
0*
b001 +
1,
0-
b001 0
#200000000
0!
0&
0,
#200432610
0#
0(
0/
#201000000
1!
1"
1&
1'
b000 +
1,
1-
b000 0
#202000000
0!
0&
0,
#202433359
#203000000
1!
1&
1,
#204000000
0!
0&
0,
#204445272
#205000000
1!
1&
1,
#206000000
0!
0&
0,
#206381135
1#
1(
1/
#207000000
1!
0"
1&
0'
b001 +
1,
0-
b001 0
#208000000
0!
0&
0,
#208091821
0#
0(
0/
#209000000
1!
1"
1&
1'
b000 +
1,
1-
b000 0
#209522097
1#
1(
1/
#210000000
0!
0&
0,
#211000000
1!
1&
b001 +
1,
b001 0
#212000000
0!
0&
0,
#212192232
0#
0(
0/
#213000000
1!
1$
1&
1)
b010 +
1,
b010 0
#214000000
0!
0&
0,
#214089013
1#
1(
1/
#215000000
1!
0$
1%
1&
0)
1*
b101 +
1,
b101 0
#216000000
0!
0&
0,
#216438776
0#
0(
0/
#217000000
1!
1$
0%
1&
1)
0*
b010 +
1,
b010 0
#218000000
0!
0&
0,
#218150850
1#
1(
1/
#219000000
1!
0"
0$
1%
1&
0'
0)
1*
b101 +
1,
0-
b101 0
#219556129
0#
0(
0/
#220000000
0!
0&
0,
#221000000
1!
1"
0%
1&
1'
0*
b000 +
1,
1-
b000 0
#222000000
0!
0&
0,
#222102881
#223000000
1!
1&
1,
#223933988
1#
1(
1/
#224000000
0!
0&
0,
#225000000
1!
1&
b001 +
1,
b001 0
#226000000
0!
0&
0,
#226043419
0#
0(
0/
#227000000
1!
1$
1&
1)
b010 +
1,
b010 0
#228000000
0!
0&
0,
#228422062
#229000000
1!
0$
1%
1&
0)
1*
b100 +
1,
b100 0
#229706750
1#
1(
1/
#230000000
0!
0&
0,
#231000000
1!
0%
1&
0*
b001 +
1,
b001 0
#232000000
0!
0&
0,
#232415553
0#
0(
0/
#233000000
1!
1$
1&
1)
b010 +
1,
b010 0
#234000000
0!
0&
0,
#234040773
1#
1(
1/
#235000000
1!
0$
1%
1&
0)
1*
b101 +
1,
b101 0
#236000000
0!
0&
0,
#236199178
#237000000
1!
1$
0%
1&
1)
0*
b011 +
1,
b011 0
#237631552
0#
0(
0/
#238000000
0!
0&
0,
#239000000
1!
0$
1&
0)
b110 +
1,
b110 0
#239576205
1#
1(
1/
#240000000
0!
0&
0,
#241000000
1!
1%
1&
1*
b101 +
1,
b101 0
#242000000
0!
0&
0,
#242350364
0#
0(
0/
#243000000
1!
1$
0%
1&
1)
0*
b010 +
1,
b010 0
#244000000
0!
0&
0,
#244465954
1#
1(
1/
#245000000
1!
0$
1%
1&
0)
1*
b101 +
1,
b101 0
#246000000
0!
0&
0,
#246217265
#247000000
1!
1$
0%
1&
1)
0*
b011 +
1,
b011 0
#248000000
0!
0&
0,
#248092371
#249000000
1!
0$
1&
0)
b111 +
1,
b111 0
#250000000
0!
0&
0,
#250291189
0#
0(
0/
#251000000
1!
1&
b110 +
1,
b110 0
#252000000
0!
0&
0,
#252012967
#253000000
1!
1%
1&
1*
b100 +
1,
b100 0
#254000000
0!
0&
0,
#254296132
#255000000
1!
0%
1&
0*
b000 +
1,
b000 0
#255938538
1#
1(
1/
#256000000
0!
0&
0,
#257000000
1!
1&
b001 +
1,
b001 0
#258000000
0!
0&
0,
#258396627
0#
0(
0/
#259000000
1!
1$
1&
1)
b010 +
1,
b010 0
#260000000
0!
0&
0,
#260093005
1#
1(
1/
#261000000
1!
0$
1%
1&
0)
1*
b101 +
1,
b101 0
#261675732
#262000000
0!
0&
0,
#263000000
1!
0"
1$
0%
1&
0'
1)
0*
b011 +
1,
0-
b011 0
#263988126
0#
0(
0/
#264000000
0!
0&
0,
#265000000
1!
1"
0$
1&
1'
0)
b000 +
1,
1-
b000 0
#266000000
0!
0&
0,
#266468020
1#
1(
1/
#267000000
1!
0"
1&
0'
b001 +
1,
0-
b001 0
#268000000
0!
0&
0,
#268297373
0#
0(
0/
#269000000
1!
1"
1&
1'
b000 +
1,
1-
b000 0
#269907384
#270000000
0!
0&
0,
#271000000
1!
1&
1,
#271805079
1#
1(
1/
#272000000
0!
0&
0,
#273000000
1!
1&
b001 +
1,
b001 0
#273613825
0#
0(
0/
#274000000
0!
0&
0,
#275000000
1!
1$
1&
1)
b010 +
1,
b010 0
#275677311
#276000000
0!
0&
0,
#277000000
1!
0$
1%
1&
0)
1*
b100 +
1,
b100 0
#277807471
#278000000
0!
0&
0,
#279000000
1!
0%
1&
0*
b000 +
1,
b000 0
#279828163
1#
1(
1/
#280000000
0!
0&
0,
#281000000
1!
1&
b001 +
1,
b001 0
#281687196
#282000000
0!
0&
0,
#283000000
1!
1$
1&
1)
b011 +
1,
b011 0
#283791778
0#
0(
0/
#284000000
0!
0&
0,
#285000000
1!
0$
1&
0)
b110 +
1,
b110 0
#286000000
0!
0&
0,
#286145103
1#
1(
1/
#287000000
1!
1%
1&
1*
b101 +
1,
b101 0
#287634296
#288000000
0!
0&
0,
#289000000
1!
1$
0%
1&
1)
0*
b011 +
1,
b011 0
#290000000
0!
0&
0,
#290272122
#291000000
1!
0$
1&
0)
b111 +
1,
b111 0
#292000000
0!
0&
0,
#292175482
0#
0(
0/
#293000000
1!
1&
b110 +
1,
b110 0
#294000000
0!
0&
0,
#294059003
1#
1(
1/
#295000000
1!
1%
1&
1*
b101 +
1,
b101 0
#295737696
0#
0(
0/
#296000000
0!
0&
0,
#297000000
1!
1$
0%
1&
1)
0*
b010 +
1,
b010 0
#297655420
#298000000
0!
0&
0,
#299000000
1!
0$
1%
1&
0)
1*
b100 +
1,
b100 0
#299649652
#300000000
0!
0&
0,
#301000000
1!
0%
1&
0*
b000 +
1,
b000 0
#302000000
0!
0&
0,
#302293376
#303000000
1!
1&
1,
#304000000
0!
0&
0,
#304307303
#305000000
1!
1&
1,
#306000000
0!
0&
0,
#306338694
1#
1(
1/
#307000000
1!
1&
b001 +
1,
b001 0
#307528543
0#
0(
0/
#308000000
0!
0&
0,
#309000000
1!
1$
1&
1)
b010 +
1,
b010 0
#309653300
#310000000
0!
0&
0,
#311000000
1!
0$
1%
1&
0)
1*
b100 +
1,
b100 0
#312000000
0!
0&
0,
#312172073
1#
1(
1/
#313000000
1!
0%
1&
0*
b001 +
1,
b001 0
#313593650
#314000000
0!
0&
0,
#315000000
1!
1$
1&
1)
b011 +
1,
b011 0
#316000000
0!
0&
0,
#316222572
0#
0(
0/
#317000000
1!
0$
1&
0)
b110 +
1,
b110 0
#317947297
#318000000
0!
0&
0,
#319000000
1!
1%
1&
1*
b100 +
1,
b100 0
#319649928
#320000000
0!
0&
0,
#321000000
1!
0%
1&
0*
b000 +
1,
b000 0
#322000000
0!
0&
0,
#322358643
#323000000
1!
1&
1,
#323537076
1#
1(
1/
#324000000
0!
0&
0,
#325000000
1!
0"
1&
0'
b001 +
1,
0-
b001 0
#326000000
0!
0&
0,
#326308443
0#
0(
0/
#327000000
1!
1"
1&
1'
b000 +
1,
1-
b000 0
#328000000
0!
0&
0,
#328042276
#329000000
1!
1&
1,
#330000000
0!
0&
0,
#330454717
1#
1(
1/
#331000000
1!
1&
b001 +
1,
b001 0
#331894767
#332000000
0!
0&
0,
#333000000
1!
1$
1&
1)
b011 +
1,
b011 0
#333668722
#334000000
0!
0&
0,
#335000000
1!
0$
1&
0)
b111 +
1,
b111 0
#335800280
0#
0(
0/
#336000000
0!
0&
0,
#337000000
1!
1&
b110 +
1,
b110 0
#338000000
0!
0&
0,
#338441160
1#
1(
1/
#339000000
1!
0"
1%
1&
0'
1*
b101 +
1,
0-
b101 0
#340000000
0!
0&
0,
#340419955
#341000000
1!
1"
0%
1&
1'
0*
b000 +
1,
1-
b000 0
#341597459
#342000000
0!
0&
0,
#343000000
1!
1&
b001 +
1,
b001 0
#344000000
0!
0&
0,
#344179197
#345000000
1!
1$
1&
1)
b011 +
1,
b011 0
#346000000
0!
0&
0,
#346316770
#347000000
1!
0$
1&
0)
b111 +
1,
b111 0
#347645498
0#
0(
0/
#348000000
0!
0&
0,
#349000000
1!
1&
b110 +
1,
b110 0
#350000000
0!
0&
0,
#350127854
1#
1(
1/
#351000000
1!
0"
1%
1&
0'
1*
b101 +
1,
0-
b101 0
#351983199
0#
0(
0/
#352000000
0!
0&
0,
#353000000
1!
1"
0%
1&
1'
0*
b000 +
1,
1-
b000 0
#354000000
0!
0&
0,
#354030307
1#
1(
1/
#355000000
1!
1&
b001 +
1,
b001 0
#355776264
0#
0(
0/
#356000000
0!
0&
0,
#357000000
1!
1$
1&
1)
b010 +
1,
b010 0
#358000000
0!
0&
0,
#358166544
#359000000
1!
0$
1%
1&
0)
1*
b100 +
1,
b100 0
#360000000
0!
0&
0,
#360167233
#361000000
1!
0%
1&
0*
b000 +
1,
b000 0
#362000000
0!
0&
0,
#362073715
#363000000
1!
0"
1&
0'
1,
0-
#363532887
#364000000
0!
0&
0,
#365000000
1!
1"
1&
1'
1,
1-
#365537442
#366000000
0!
0&
0,
#367000000
1!
1&
1,
#367814918
#368000000
0!
0&
0,
#369000000
1!
1&
1,
#370000000
0!
0&
0,
#370377050
1#
1(
1/
#371000000
1!
1&
b001 +
1,
b001 0
#372000000
0!
0&
0,
#372005260
0#
0(
0/
#373000000
1!
1$
1&
1)
b010 +
1,
b010 0
#373642813
1#
1(
1/
#374000000
0!
0&
0,
#375000000
1!
0$
1%
1&
0)
1*
b101 +
1,
b101 0
#376000000
0!
0&
0,
#376103397
#377000000
1!
1$
0%
1&
1)
0*
b011 +
1,
b011 0
#377720879
0#
0(
0/
#378000000
0!
0&
0,
#379000000
1!
0"
0$
1&
0'
0)
b110 +
1,
0-
b110 0
#380000000
0!
0&
0,
#380138792
1#
1(
1/
#381000000
1!
1&
b000 +
1,
b000 0
#381845416
0#
0(
0/
#382000000
0!
0&
0,
#383000000
1!
1"
1&
1'
1,
1-
#384000000
0!
0&
0,
#384338110
#385000000
1!
1&
1,
#385928490
#386000000
0!
0&
0,
#387000000
1!
1&
1,
#387522422
#388000000
0!
0&
0,
#389000000
1!
1&
1,
#390000000
0!
0&
0,
#390271177
#391000000
1!
1&
1,
#392000000
0!
0&
0,
#392236299
#393000000
1!
1&
1,
#393782265
#394000000
0!
0&
0,
#395000000
1!
1&
1,
#395926936
#396000000
0!
0&
0,
#397000000
1!
1&
1,
#398000000
0!
0&
0,
#398282232
#399000000
1!
1&
1,
#399562445
#400000000
0!
0&
0,
#401000000
1!
1&
1,
#401960432
#402000000
0!
0&
0,
#403000000
1!
1&
1,
#404000000
0!
0&
0,
#404003003
#405000000
1!
1&
1,
#406000000
0!
0&
0,
#406393598
#407000000
1!
1&
1,
#408000000
0!
0&
0,
#408397977
1#
1(
1/
#409000000
1!
1&
b001 +
1,
b001 0
#409985116
0#
0(
0/
#410000000
0!
0&
0,
#411000000
1!
1$
1&
1)
b010 +
1,
b010 0
#412000000
0!
0&
0,
#412284793
1#
1(
1/
#413000000
1!
0$
1%
1&
0)
1*
b101 +
1,
b101 0
#414000000
0!
0&
0,
#414494799
0#
0(
0/
#415000000
1!
1$
0%
1&
1)
0*
b010 +
1,
b010 0
#416000000
0!
0&
0,
#416396409
#417000000
1!
0$
1%
1&
0)
1*
b100 +
1,
b100 0
#417902731
#418000000
0!
0&
0,
#419000000
1!
0%
1&
0*
b000 +
1,
b000 0
#420000000
0!
0&
0,
#420169363
#421000000
1!
1&
1,
#421855104
1#
1(
1/
#422000000
0!
0&
0,
#423000000
1!
0"
1&
0'
b001 +
1,
0-
b001 0
#424000000
0!
0&
0,
#424381886
0#
0(
0/
#425000000
1!
1"
1&
1'
b000 +
1,
1-
b000 0
#425865450
#426000000
0!
0&
0,
#427000000
1!
1&
1,
#428000000
0!
0&
0,
#428350855
1#
1(
1/
#429000000
1!
1&
b001 +
1,
b001 0
#430000000
0!
0&
0,
#430139643
0#
0(
0/
#431000000
1!
1$
1&
1)
b010 +
1,
b010 0
#432000000
0!
0&
0,
#432002907
#433000000
1!
0$
1%
1&
0)
1*
b100 +
1,
b100 0
#434000000
0!
0&
0,
#434117085
#435000000
1!
0"
0%
1&
0'
0*
b000 +
1,
0-
b000 0
#435513948
1#
1(
1/
#436000000
0!
0&
0,
#437000000
1!
1"
1&
1'
1,
1-
#438000000
0!
0&
0,
#438304267
0#
0(
0/
#439000000
1!
1&
1,
#440000000
0!
0&
0,
#440016921
1#
1(
1/
#441000000
1!
1&
b001 +
1,
b001 0
#441806846
0#
0(
0/
#442000000
0!
0&
0,
#443000000
1!
1$
1&
1)
b010 +
1,
b010 0
#443838905
#444000000
0!
0&
0,
#445000000
1!
0$
1%
1&
0)
1*
b100 +
1,
b100 0
#446000000
0!
0&
0,
#446257447
#447000000
1!
0"
0%
1&
0'
0*
b000 +
1,
0-
b000 0
#447823191
#448000000
0!
0&
0,
#449000000
1!
1&
1,
#450000000
0!
0&
0,
#450017424
#451000000
1!
1"
1&
1'
1,
1-
#452000000
0!
0&
0,
#452143871
#453000000
1!
1&
1,
#454000000
0!
0&
0,
#454187444
#455000000
1!
1&
1,
#456000000
0!
0&
0,
#456142201
1#
1(
1/
#457000000
1!
1&
b001 +
1,
b001 0
#457666576
0#
0(
0/
#458000000
0!
0&
0,
#459000000
1!
1$
1&
1)
b010 +
1,
b010 0
#459551016
1#
1(
1/
#460000000
0!
0&
0,
#461000000
1!
0$
1%
1&
0)
1*
b101 +
1,
b101 0
#461793840
0#
0(
0/
#462000000
0!
0&
0,
#463000000
1!
1$
0%
1&
1)
0*
b010 +
1,
b010 0
#464000000
0!
0&
0,
#464265557
1#
1(
1/
#465000000
1!
0$
1%
1&
0)
1*
b101 +
1,
b101 0
#466000000
0!
0&
0,
#466217156
0#
0(
0/
#467000000
1!
1$
0%
1&
1)
0*
b010 +
1,
b010 0
#468000000
0!
0&
0,
#468112724
#469000000
1!
0$
1%
1&
0)
1*
b100 +
1,
b100 0
#469506569
#470000000
0!
0&
0,
#471000000
1!
0%
1&
0*
b000 +
1,
b000 0
#472000000
0!
0&
0,
#472360762
#473000000
1!
1&
1,
#473634845
#474000000
0!
0&
0,
#475000000
1!
1&
1,
#476000000
0!
0&
0,
#476439480
1#
1(
1/
#477000000
1!
0"
1&
0'
b001 +
1,
0-
b001 0
#478000000
0!
0&
0,
#478272094
#479000000
1!
1"
1&
1'
b000 +
1,
1-
b000 0
#480000000
0!
0&
0,
#480468634
#481000000
1!
1&
b001 +
1,
b001 0
#481986902
0#
0(
0/
#482000000
0!
0&
0,
#483000000
1!
1$
1&
1)
b010 +
1,
b010 0
#483877936
#484000000
0!
0&
0,
#485000000
1!
0$
1%
1&
0)
1*
b100 +
1,
b100 0
#486000000
0!
0&
0,
#486455403
#487000000
1!
0%
1&
0*
b000 +
1,
b000 0
#487675477
1#
1(
1/
#488000000
0!
0&
0,
#489000000
1!
1&
b001 +
1,
b001 0
#490000000
0!
0&
0,
#490113099
0#
0(
0/
#491000000
1!
1$
1&
1)
b010 +
1,
b010 0
#492000000
0!
0&
0,
#492484874
#493000000
1!
0$
1%
1&
0)
1*
b100 +
1,
b100 0
#494000000
0!
0&
0,
#494435565
1#
1(
1/
#495000000
1!
0"
0%
1&
0'
0*
b001 +
1,
0-
b001 0
#495861424
0#
0(
0/
#496000000
0!
0&
0,
#497000000
1!
1"
1&
1'
b000 +
1,
1-
b000 0
#498000000
0!
0&
0,
#498409977
#499000000
1!
1&
1,
#499625001
1#
1(
1/
#500000000
0!
0&
0,
#501000000
1!
1&
b001 +
1,
b001 0
#501664186
#502000000
0!
0&
0,
#503000000
1!
1$
1&
1)
b011 +
1,
b011 0
#503866870
#504000000
0!
0&
0,
#505000000
1!
0$
1&
0)
b111 +
1,
b111 0
#506000000
0!
0&
0,
#506185444
0#
0(
0/
#507000000
1!
1&
b110 +
1,
b110 0
#507857852
1#
1(
1/
#508000000
0!
0&
0,
#509000000
1!
1%
1&
1*
b101 +
1,
b101 0
#509903849
#510000000
0!
0&
0,
#511000000
1!
1$
0%
1&
1)
0*
b011 +
1,
b011 0
#512000000
0!
0&
0,
#512246132
0#
0(
0/
#513000000
1!
0"
0$
1&
0'
0)
b110 +
1,
0-
b110 0
#514000000
0!
0&
0,
#514331761
#515000000
1!
1"
1&
1'
b000 +
1,
1-
b000 0
#516000000
0!
0&
0,
