vhdl/lab02/sr.vhd
library ieee;
use ieee.std_logic_1164.all;
use ieee.numeric_std_unsigned.all;


entity sr is
  generic(
    n : positive := 16
  );
  port(
    clk     : in  std_ulogic;
    sresetn : in  std_ulogic;
    shift   : in  std_ulogic;
    din     : in  std_ulogic;
    dout    : out std_ulogic_vector(n-1 downto 0)
  );
end entity sr;

architecture rtl of sr is
  begin
  process(clk)
  begin
    if rising_edge(clk) then
      if not sresetn then
        dout <= (others => '0');
      else
        if shift then
          dout <= dout(n-2 downto 0) & din;
        end if;
      end if;
    end if;
  end process;
end architecture rtl;

vhdl/lab02/sr_sim.vhd
-- MASTER-ONLY: DO NOT MODIFY THIS FILE
--
-- Copyright (C) Telecom Paris
-- Copyright (C) Renaud Pacalet (renaud.pacalet@telecom-paris.fr)
-- 
-- This file must be used under the terms of the CeCILL. This source
-- file is licensed as described in the file COPYING, which you should
-- have received as part of this distribution. The terms are also
-- available at:
-- http://www.cecill.info/licences/Licence_CeCILL_V1.1-US.txt
--

-- The simulation environment has no inputs and no outputs. It is a black box
-- representing the whole universe.
entity sr_sim is
    generic(d: positive := 1000); -- Duration of test in clock cycles
end entity sr_sim;

-- For the "finish" procedure.
use std.env.all;

-- For the "std_ulogic" and "std_ulogic_vector" types.
library ieee;
use ieee.std_logic_1164.all;

-- "common.rnd_pkg" defines the "rnd_generator" protected type and all the
-- companion procedures and functions.
library common;
use common.rnd_pkg.all;

architecture sim of sr_sim is

    -- The signals that will connect the "sr" instance to its environment. They
    -- have the same names as the ports of "sr" because it is a natural choice
    -- but it is not mandatory at all.
    signal clk:      std_ulogic;
    signal sresetn:  std_ulogic;
    signal shift:    std_ulogic;
    signal din:      std_ulogic;
    signal dout:     std_ulogic_vector(3 downto 0);

begin

    -- Instance of "sr", named "dut" (for Design Under Test). The format of the
    -- associations is:
    --   generic-parameter-name => value
    --   port-name => signal
    -- Implicit ordered associations are also possible:
    --   generic map(4)
    --   port map(clk, sresetn, shift, din, dout)
    -- but they are less flexible and must consider the order of the
    -- declarations in entity "sr".
    dut: entity work.sr(rtl)
    generic map(n => 4)
    port map(
        clk     => clk,
        sresetn => sresetn,
        shift   => shift,
        din     => din,
        dout    => dout
    );

    -- Infinite 500 MHz clock generator.
    process
    begin
        clk <= '0';
        wait for 1 ns;
        clk <= '1';
        wait for 1 ns;
    end process;

    -- Generator of the other inputs of "sr".
    process
        -- A random generator
        variable r: rnd_generator;
    begin
        -- Start with a reset phase.
        sresetn <= '0';
        shift   <= '0';
        din     <= '0';
        -- Let 10 rising edges of clock go.
        for i in 1 to 10 loop
            wait until rising_edge(clk);
        end loop;
        -- Deassert reset signal.
        sresetn <= '1';
        -- Loop over "d" clock cycles.
        for i in 1 to d loop
            -- Since VHDL 2008 the conditional when signal assignment is usable
            -- in processes. This one asserts the reset with probability 1/10.
            if r.get_integer(1, 10) = 1 then
                sresetn <= '0';
            else
                sresetn <= '1';
            end if;
            -- Assign uniform random values to "shift" and "din". The aggregate
            -- notation can be used in the LHS of assignments.
            (shift, din) <= r.get_std_ulogic_vector(2);
            -- Wait until next rising edge of clock (necessary for the applied
            -- stimulus to be taken into account by the "sr" instance).
            wait until rising_edge(clk);
        end loop;
        -- The "finish" procedure of the "std.env" package terminates the
        -- simulation. It has been introduced in VHDL 2008. Prior this,
        -- gracefully ending a simulation was a bit more difficult.
        finish;
    end process;

end architecture sim;

-- vim: set tabstop=4 softtabstop=4 shiftwidth=4 expandtab textwidth=0:

sim/sr_sim.vcd
$date
  Tue Mar  8 16:14:58 2022
$end
$version
  GHDL v0
$end
$timescale
  1 fs
$end
$scope module standard $end
$upscope $end
$scope module env $end
$upscope $end
$scope module textio $end
$upscope $end
$scope module std_logic_1164 $end
$upscope $end
$scope module rnd_pkg $end
$upscope $end
$scope module math_real $end
$upscope $end
$scope module numeric_std_unsigned $end
$upscope $end
$scope module numeric_std $end
$upscope $end
$scope module sr_sim $end
$var reg 1 ! clk $end
$var reg 1 " sresetn $end
$var reg 1 # shift $end
$var reg 1 $ din $end
$var reg 4 % dout[3:0] $end
$scope module dut $end
$var reg 1 & clk $end
$var reg 1 ' sresetn $end
$var reg 1 ( shift $end
$var reg 1 ) din $end
$var reg 4 * dout[3:0] $end
$upscope $end
$upscope $end
$enddefinitions $end
#0
0!
0"
0#
0$
bUUUU %
0&
0'
0(
0)
bUUUU *
#1000000
1!
b0000 %
1&
b0000 *
#2000000
0!
0&
#3000000
1!
1&
#4000000
0!
0&
#5000000
1!
1&
#6000000
0!
0&
#7000000
1!
1&
#8000000
0!
0&
#9000000
1!
1&
#10000000
0!
0&
#11000000
1!
1&
#12000000
0!
0&
#13000000
1!
1&
#14000000
0!
0&
#15000000
1!
1&
#16000000
0!
0&
#17000000
1!
1&
#18000000
0!
0&
#19000000
1!
1"
1#
1$
1&
1'
1(
1)
#20000000
0!
0&
#21000000
1!
0#
0$
b0001 %
1&
0(
0)
b0001 *
#22000000
0!
0&
#23000000
1!
1&
#24000000
0!
0&
#25000000
1!
1$
1&
1)
#26000000
0!
0&
#27000000
1!
0$
1&
0)
#28000000
0!
0&
#29000000
1!
1#
1$
1&
1(
1)
#30000000
0!
0&
#31000000
1!
0"
b0011 %
1&
0'
b0011 *
#32000000
0!
0&
#33000000
1!
1"
0#
0$
b0000 %
1&
1'
0(
0)
b0000 *
#34000000
0!
0&
#35000000
1!
1#
1&
1(
#36000000
0!
0&
#37000000
1!
1&
#38000000
0!
0&
#39000000
1!
0"
1&
0'
#40000000
0!
0&
#41000000
1!
1"
0#
1&
1'
0(
#42000000
0!
0&
#43000000
1!
1&
#44000000
0!
0&
#45000000
1!
1#
1&
1(
#46000000
0!
0&
#47000000
1!
0"
0#
1&
0'
0(
#48000000
0!
0&
#49000000
1!
1"
1&
1'
#50000000
0!
0&
#51000000
1!
1$
1&
1)
#52000000
0!
0&
#53000000
1!
1#
0$
1&
1(
0)
#54000000
0!
0&
#55000000
1!
0#
1$
1&
0(
1)
#56000000
0!
0&
#57000000
1!
0$
1&
0)
#58000000
0!
0&
#59000000
1!
1#
1$
1&
1(
1)
#60000000
0!
0&
#61000000
1!
0#
b0001 %
1&
0(
b0001 *
#62000000
0!
0&
#63000000
1!
1#
1&
1(
#64000000
0!
0&
#65000000
1!
0$
b0011 %
1&
0)
b0011 *
#66000000
0!
0&
#67000000
1!
0#
1$
b0110 %
1&
0(
1)
b0110 *
#68000000
0!
0&
#69000000
1!
1#
0$
1&
1(
0)
#70000000
0!
0&
#71000000
1!
b1100 %
1&
b1100 *
#72000000
0!
0&
#73000000
1!
0#
b1000 %
1&
0(
b1000 *
#74000000
0!
0&
#75000000
1!
1&
#76000000
0!
0&
#77000000
1!
0"
1&
0'
#78000000
0!
0&
#79000000
1!
1"
1$
b0000 %
1&
1'
1)
b0000 *
#80000000
0!
0&
#81000000
1!
0$
1&
0)
#82000000
0!
0&
#83000000
1!
1#
1&
1(
#84000000
0!
0&
#85000000
1!
0#
1$
1&
0(
1)
#86000000
0!
0&
#87000000
1!
1&
#88000000
0!
0&
#89000000
1!
0$
1&
0)
#90000000
0!
0&
#91000000
1!
1&
#92000000
0!
0&
#93000000
1!
1#
1$
1&
1(
1)
#94000000
0!
0&
#95000000
1!
0"
0#
b0001 %
1&
0'
0(
b0001 *
#96000000
0!
0&
#97000000
1!
1"
1#
b0000 %
1&
1'
1(
b0000 *
#98000000
0!
0&
#99000000
1!
0$
b0001 %
1&
0)
b0001 *
#100000000
0!
0&
#101000000
1!
b0010 %
1&
b0010 *
#102000000
0!
0&
#103000000
1!
b0100 %
1&
b0100 *
#104000000
0!
0&
#105000000
1!
1$
b1000 %
1&
1)
b1000 *
#106000000
0!
0&
#107000000
1!
0$
b0001 %
1&
0)
b0001 *
#108000000
0!
0&
#109000000
1!
0#
1$
b0010 %
1&
0(
1)
b0010 *
#110000000
0!
0&
#111000000
1!
0$
1&
0)
#112000000
0!
0&
#113000000
1!
1&
#114000000
0!
0&
#115000000
1!
1$
1&
1)
#116000000
0!
0&
#117000000
1!
1&
#118000000
0!
0&
#119000000
1!
1&
#120000000
0!
0&
#121000000
1!
0$
1&
0)
#122000000
0!
0&
#123000000
1!
1#
1$
1&
1(
1)
#124000000
0!
0&
#125000000
1!
b0101 %
1&
b0101 *
#126000000
0!
0&
#127000000
1!
b1011 %
1&
b1011 *
#128000000
0!
0&
#129000000
1!
0#
b0111 %
1&
0(
b0111 *
#130000000
0!
0&
#131000000
1!
0$
1&
0)
#132000000
0!
0&
#133000000
1!
1#
1&
1(
#134000000
0!
0&
#135000000
1!
b1110 %
1&
b1110 *
#136000000
0!
0&
#137000000
1!
b1100 %
1&
b1100 *
#138000000
0!
0&
#139000000
1!
0"
0#
b1000 %
1&
0'
0(
b1000 *
#140000000
0!
0&
#141000000
1!
1"
1$
b0000 %
1&
1'
1)
b0000 *
#142000000
0!
0&
#143000000
1!
0$
1&
0)
#144000000
0!
0&
#145000000
1!
0"
1#
1$
1&
0'
1(
1)
#146000000
0!
0&
#147000000
1!
1"
0#
0$
1&
1'
0(
0)
#148000000
0!
0&
#149000000
1!
1&
#150000000
0!
0&
#151000000
1!
0"
1$
1&
0'
1)
#152000000
0!
0&
#153000000
1!
1"
1&
1'
#154000000
0!
0&
#155000000
1!
0$
1&
0)
#156000000
0!
0&
#157000000
1!
1$
1&
1)
#158000000
0!
0&
#159000000
1!
1#
1&
1(
#160000000
0!
0&
#161000000
1!
0#
b0001 %
1&
0(
b0001 *
#162000000
0!
0&
#163000000
1!
1#
1&
1(
#164000000
0!
0&
#165000000
1!
0#
b0011 %
1&
0(
b0011 *
#166000000
0!
0&
#167000000
1!
1#
0$
1&
1(
0)
#168000000
0!
0&
#169000000
1!
0#
1$
b0110 %
1&
0(
1)
b0110 *
#170000000
0!
0&
#171000000
1!
1#
1&
1(
#172000000
0!
0&
#173000000
1!
b1101 %
1&
b1101 *
#174000000
0!
0&
#175000000
1!
0#
b1011 %
1&
0(
b1011 *
#176000000
0!
0&
#177000000
1!
1&
#178000000
0!
0&
#179000000
1!
0"
1#
0$
1&
0'
1(
0)
#180000000
0!
0&
#181000000
1!
1"
0#
1$
b0000 %
1&
1'
0(
1)
b0000 *
#182000000
0!
0&
#183000000
1!
1#
0$
1&
1(
0)
#184000000
0!
0&
#185000000
1!
1$
1&
1)
#186000000
0!
0&
#187000000
1!
0#
0$
b0001 %
1&
0(
0)
b0001 *
#188000000
0!
0&
#189000000
1!
1#
1&
1(
#190000000
0!
0&
#191000000
1!
b0010 %
1&
b0010 *
#192000000
0!
0&
#193000000
1!
0#
b0100 %
1&
0(
b0100 *
#194000000
0!
0&
#195000000
1!
1&
#196000000
0!
0&
#197000000
1!
1#
1$
1&
1(
1)
#198000000
0!
0&
#199000000
1!
0"
0#
b1001 %
1&
0'
0(
b1001 *
#200000000
0!
0&
#201000000
1!
1"
b0000 %
1&
1'
b0000 *
#202000000
0!
0&
#203000000
1!
1&
#204000000
0!
0&
#205000000
1!
1#
1&
1(
#206000000
0!
0&
#207000000
1!
0"
0#
b0001 %
1&
0'
0(
b0001 *
#208000000
0!
0&
#209000000
1!
1"
1#
0$
b0000 %
1&
1'
1(
0)
b0000 *
#210000000
0!
0&
#211000000
1!
0#
1$
1&
0(
1)
#212000000
0!
0&
#213000000
1!
1#
1&
1(
#214000000
0!
0&
#215000000
1!
0#
b0001 %
1&
0(
b0001 *
#216000000
0!
0&
#217000000
1!
1#
1&
1(
#218000000
0!
0&
#219000000
1!
0"
0#
0$
b0011 %
1&
0'
0(
0)
b0011 *
#220000000
0!
0&
#221000000
1!
1"
1$
b0000 %
1&
1'
1)
b0000 *
#222000000
0!
0&
#223000000
1!
1#
0$
1&
1(
0)
#224000000
0!
0&
#225000000
1!
0#
1$
1&
0(
1)
#226000000
0!
0&
#227000000
1!
1&
#228000000
0!
0&
#229000000
1!
1#
0$
1&
1(
0)
#230000000
0!
0&
#231000000
1!
0#
1$
1&
0(
1)
#232000000
0!
0&
#233000000
1!
1#
1&
1(
#234000000
0!
0&
#235000000
1!
b0001 %
1&
b0001 *
#236000000
0!
0&
#237000000
1!
0#
0$
b0011 %
1&
0(
0)
b0011 *
#238000000
0!
0&
#239000000
1!
1#
1&
1(
#240000000
0!
0&
#241000000
1!
0#
1$
b0110 %
1&
0(
1)
b0110 *
#242000000
0!
0&
#243000000
1!
1#
1&
1(
#244000000
0!
0&
#245000000
1!
b1101 %
1&
b1101 *
#246000000
0!
0&
#247000000
1!
b1011 %
1&
b1011 *
#248000000
0!
0&
#249000000
1!
0#
b0111 %
1&
0(
b0111 *
#250000000
0!
0&
#251000000
1!
1&
#252000000
0!
0&
#253000000
1!
1&
#254000000
0!
0&
#255000000
1!
1#
0$
1&
1(
0)
#256000000
0!
0&
#257000000
1!
0#
1$
b1110 %
1&
0(
1)
b1110 *
#258000000
0!
0&
#259000000
1!
1#
1&
1(
#260000000
0!
0&
#261000000
1!
0$
b1101 %
1&
0)
b1101 *
#262000000
0!
0&
#263000000
1!
0"
0#
b1010 %
1&
0'
0(
b1010 *
#264000000
0!
0&
#265000000
1!
1"
1#
1$
b0000 %
1&
1'
1(
1)
b0000 *
#266000000
0!
0&
#267000000
1!
0"
0#
b0001 %
1&
0'
0(
b0001 *
#268000000
0!
0&
#269000000
1!
1"
0$
b0000 %
1&
1'
0)
b0000 *
#270000000
0!
0&
#271000000
1!
1#
1&
1(
#272000000
0!
0&
#273000000
1!
0#
1&
0(
#274000000
0!
0&
#275000000
1!
1&
#276000000
0!
0&
#277000000
1!
1&
#278000000
0!
0&
#279000000
1!
1#
1&
1(
#280000000
0!
0&
#281000000
1!
1&
#282000000
0!
0&
#283000000
1!
0#
1&
0(
#284000000
0!
0&
#285000000
1!
1#
1$
1&
1(
1)
#286000000
0!
0&
#287000000
1!
0$
b0001 %
1&
0)
b0001 *
#288000000
0!
0&
#289000000
1!
1$
b0010 %
1&
1)
b0010 *
#290000000
0!
0&
#291000000
1!
0#
b0101 %
1&
0(
b0101 *
#292000000
0!
0&
#293000000
1!
1#
1&
1(
#294000000
0!
0&
#295000000
1!
0#
0$
b1011 %
1&
0(
0)
b1011 *
#296000000
0!
0&
#297000000
1!
1&
#298000000
0!
0&
#299000000
1!
1&
#300000000
0!
0&
#301000000
1!
1$
1&
1)
#302000000
0!
0&
#303000000
1!
1&
#304000000
0!
0&
#305000000
1!
1#
1&
1(
#306000000
0!
0&
#307000000
1!
0#
0$
b0111 %
1&
0(
0)
b0111 *
#308000000
0!
0&
#309000000
1!
1&
#310000000
0!
0&
#311000000
1!
1#
1$
1&
1(
1)
#312000000
0!
0&
#313000000
1!
0$
b1111 %
1&
0)
b1111 *
#314000000
0!
0&
#315000000
1!
0#
1$
b1110 %
1&
0(
1)
b1110 *
#316000000
0!
0&
#317000000
1!
0$
1&
0)
#318000000
0!
0&
#319000000
1!
1&
#320000000
0!
0&
#321000000
1!
1$
1&
1)
#322000000
0!
0&
#323000000
1!
1#
0$
1&
1(
0)
#324000000
0!
0&
#325000000
1!
0"
0#
1$
b1100 %
1&
0'
0(
1)
b1100 *
#326000000
0!
0&
#327000000
1!
1"
b0000 %
1&
1'
b0000 *
#328000000
0!
0&
#329000000
1!
1#
1&
1(
#330000000
0!
0&
#331000000
1!
0$
b0001 %
1&
0)
b0001 *
#332000000
0!
0&
#333000000
1!
b0010 %
1&
b0010 *
#334000000
0!
0&
#335000000
1!
0#
b0100 %
1&
0(
b0100 *
#336000000
0!
0&
#337000000
1!
1#
1$
1&
1(
1)
#338000000
0!
0&
#339000000
1!
0"
b1001 %
1&
0'
b1001 *
#340000000
0!
0&
#341000000
1!
1"
0$
b0000 %
1&
1'
0)
b0000 *
#342000000
0!
0&
#343000000
1!
1$
1&
1)
#344000000
0!
0&
#345000000
1!
b0001 %
1&
b0001 *
#346000000
0!
0&
#347000000
1!
0#
0$
b0011 %
1&
0(
0)
b0011 *
#348000000
0!
0&
#349000000
1!
1#
1$
1&
1(
1)
#350000000
0!
0&
#351000000
1!
0"
0#
0$
b0111 %
1&
0'
0(
0)
b0111 *
#352000000
0!
0&
#353000000
1!
1"
1#
1$
b0000 %
1&
1'
1(
1)
b0000 *
#354000000
0!
0&
#355000000
1!
0#
0$
b0001 %
1&
0(
0)
b0001 *
#356000000
0!
0&
#357000000
1!
1$
1&
1)
#358000000
0!
0&
#359000000
1!
1&
#360000000
0!
0&
#361000000
1!
1&
#362000000
0!
0&
#363000000
1!
0"
0$
1&
0'
0)
#364000000
0!
0&
#365000000
1!
1"
b0000 %
1&
1'
b0000 *
#366000000
0!
0&
#367000000
1!
1&
#368000000
0!
0&
#369000000
1!
1#
1$
1&
1(
1)
#370000000
0!
0&
#371000000
1!
0#
b0001 %
1&
0(
b0001 *
#372000000
0!
0&
#373000000
1!
1#
0$
1&
1(
0)
#374000000
0!
0&
#375000000
1!
1$
b0010 %
1&
1)
b0010 *
#376000000
0!
0&
#377000000
1!
0#
0$
b0101 %
1&
0(
0)
b0101 *
#378000000
0!
0&
#379000000
1!
0"
1#
1$
1&
0'
1(
1)
#380000000
0!
0&
#381000000
1!
0#
0$
b0000 %
1&
0(
0)
b0000 *
#382000000
0!
0&
#383000000
1!
1"
1$
1&
1'
1)
#384000000
0!
0&
#385000000
1!
0$
1&
0)
#386000000
0!
0&
#387000000
1!
1&
#388000000
0!
0&
#389000000
1!
1$
1&
1)
#390000000
0!
0&
#391000000
1!
1&
#392000000
0!
0&
#393000000
1!
0$
1&
0)
#394000000
0!
0&
#395000000
1!
1&
#396000000
0!
0&
#397000000
1!
1$
1&
1)
#398000000
0!
0&
#399000000
1!
0$
1&
0)
#400000000
0!
0&
#401000000
1!
1&
#402000000
0!
0&
#403000000
1!
1$
1&
1)
#404000000
0!
0&
#405000000
1!
1&
#406000000
0!
0&
#407000000
1!
1#
1&
1(
#408000000
0!
0&
#409000000
1!
0#
0$
b0001 %
1&
0(
0)
b0001 *
#410000000
0!
0&
#411000000
1!
1#
1$
1&
1(
1)
#412000000
0!
0&
#413000000
1!
0#
b0011 %
1&
0(
b0011 *
#414000000
0!
0&
#415000000
1!
1&
#416000000
0!
0&
#417000000
1!
0$
1&
0)
#418000000
0!
0&
#419000000
1!
1$
1&
1)
#420000000
0!
0&
#421000000
1!
1#
0$
1&
1(
0)
#422000000
0!
0&
#423000000
1!
0"
0#
1$
b0110 %
1&
0'
0(
1)
b0110 *
#424000000
0!
0&
#425000000
1!
1"
0$
b0000 %
1&
1'
0)
b0000 *
#426000000
0!
0&
#427000000
1!
1#
1$
1&
1(
1)
#428000000
0!
0&
#429000000
1!
0#
b0001 %
1&
0(
b0001 *
#430000000
0!
0&
#431000000
1!
1&
#432000000
0!
0&
#433000000
1!
1&
#434000000
0!
0&
#435000000
1!
0"
1#
0$
1&
0'
1(
0)
#436000000
0!
0&
#437000000
1!
1"
0#
1$
b0000 %
1&
1'
0(
1)
b0000 *
#438000000
0!
0&
#439000000
1!
1#
1&
1(
#440000000
0!
0&
#441000000
1!
0#
0$
b0001 %
1&
0(
0)
b0001 *
#442000000
0!
0&
#443000000
1!
1&
#444000000
0!
0&
#445000000
1!
1$
1&
1)
#446000000
0!
0&
#447000000
1!
0"
0$
1&
0'
0)
#448000000
0!
0&
#449000000
1!
1$
b0000 %
1&
1)
b0000 *
#450000000
0!
0&
#451000000
1!
1"
1&
1'
#452000000
0!
0&
#453000000
1!
1&
#454000000
0!
0&
#455000000
1!
1#
1&
1(
#456000000
0!
0&
#457000000
1!
0#
0$
b0001 %
1&
0(
0)
b0001 *
#458000000
0!
0&
#459000000
1!
1#
1&
1(
#460000000
0!
0&
#461000000
1!
0#
b0010 %
1&
0(
b0010 *
#462000000
0!
0&
#463000000
1!
1#
1$
1&
1(
1)
#464000000
0!
0&
#465000000
1!
0#
b0101 %
1&
0(
b0101 *
#466000000
0!
0&
#467000000
1!
1&
#468000000
0!
0&
#469000000
1!
0$
1&
0)
#470000000
0!
0&
#471000000
1!
1$
1&
1)
#472000000
0!
0&
#473000000
1!
0$
1&
0)
#474000000
0!
0&
#475000000
1!
1#
1$
1&
1(
1)
#476000000
0!
0&
#477000000
1!
0"
b1011 %
1&
0'
b1011 *
#478000000
0!
0&
#479000000
1!
1"
b0000 %
1&
1'
b0000 *
#480000000
0!
0&
#481000000
1!
0#
0$
b0001 %
1&
0(
0)
b0001 *
#482000000
0!
0&
#483000000
1!
1&
#484000000
0!
0&
#485000000
1!
1$
1&
1)
#486000000
0!
0&
#487000000
1!
1#
0$
1&
1(
0)
#488000000
0!
0&
#489000000
1!
0#
1$
b0010 %
1&
0(
1)
b0010 *
#490000000
0!
0&
#491000000
1!
1&
#492000000
0!
0&
#493000000
1!
1#
1&
1(
#494000000
0!
0&
#495000000
1!
0"
0#
0$
b0101 %
1&
0'
0(
0)
b0101 *
#496000000
0!
0&
#497000000
1!
1"
1$
b0000 %
1&
1'
1)
b0000 *
#498000000
0!
0&
#499000000
1!
1#
0$
1&
1(
0)
#500000000
0!
0&
#501000000
1!
1&
#502000000
0!
0&
#503000000
1!
1&
#504000000
0!
0&
#505000000
1!
0#
1$
1&
0(
1)
#506000000
0!
0&
#507000000
1!
1#
0$
1&
1(
0)
#508000000
0!
0&
#509000000
1!
1&
#510000000
0!
0&
#511000000
1!
0#
1$
1&
0(
1)
#512000000
0!
0&
#513000000
1!
0"
1&
0'
#514000000
0!
0&
#515000000
1!
1"
1&
1'
#516000000
0!
0&
#517000000
1!
1&
#518000000
0!
0&
#519000000
1!
1#
1&
1(
#520000000
0!
0&
#521000000
1!
0#
b0001 %
1&
0(
b0001 *
#522000000
0!
0&
#523000000
1!
0"
1#
0$
1&
0'
1(
0)
#524000000
0!
0&
#525000000
1!
1"
0#
1$
b0000 %
1&
1'
0(
1)
b0000 *
#526000000
0!
0&
#527000000
1!
1#
0$
1&
1(
0)
#528000000
0!
0&
#529000000
1!
0#
1&
0(
#530000000
0!
0&
#531000000
1!
1#
1&
1(
#532000000
0!
0&
#533000000
1!
1$
1&
1)
#534000000
0!
0&
#535000000
1!
0"
b0001 %
1&
0'
b0001 *
#536000000
0!
0&
#537000000
1!
1"
0#
0$
b0000 %
1&
1'
0(
0)
b0000 *
#538000000
0!
0&
#539000000
1!
1#
1&
1(
#540000000
0!
0&
#541000000
1!
0"
1$
1&
0'
1)
#542000000
0!
0&
#543000000
1!
1"
0#
0$
1&
1'
0(
0)
#544000000
0!
0&
#545000000
1!
1$
1&
1)
#546000000
0!
0&
#547000000
1!
1&
#548000000
0!
0&
#549000000
1!
1#
0$
1&
1(
0)
#550000000
0!
0&
#551000000
1!
0#
1$
1&
0(
1)
#552000000
0!
0&
#553000000
1!
0$
1&
0)
#554000000
0!
0&
#555000000
1!
0"
1$
1&
0'
1)
#556000000
0!
0&
#557000000
1!
1"
1#
1&
1'
1(
#558000000
0!
0&
#559000000
1!
0$
b0001 %
1&
0)
b0001 *
#560000000
0!
0&
#561000000
1!
0#
b0010 %
1&
0(
b0010 *
#562000000
0!
0&
#563000000
1!
0"
1#
1&
0'
1(
#564000000
0!
0&
#565000000
1!
1"
0#
1$
b0000 %
1&
1'
0(
1)
b0000 *
#566000000
0!
0&
#567000000
1!
0$
1&
0)
#568000000
0!
0&
#569000000
1!
0"
1#
1$
1&
0'
1(
1)
#570000000
0!
0&
#571000000
1!
1"
0$
1&
1'
0)
#572000000
0!
0&
#573000000
1!
1&
#574000000
0!
0&
#575000000
1!
0"
1$
1&
0'
1)
#576000000
0!
0&
#577000000
1!
1"
0$
1&
1'
0)
#578000000
0!
0&
#579000000
1!
0"
0#
1&
0'
0(
#580000000
0!
0&
#581000000
1!
1"
1#
1&
1'
1(
#582000000
0!
0&
#583000000
1!
0#
1$
1&
0(
1)
#584000000
0!
0&
#585000000
1!
1&
#586000000
0!
0&
#587000000
1!
1&
#588000000
0!
0&
#589000000
1!
1#
0$
1&
1(
0)
#590000000
0!
0&
#591000000
1!
0#
1&
0(
#592000000
0!
0&
#593000000
1!
1#
1$
1&
1(
1)
#594000000
0!
0&
#595000000
1!
0#
b0001 %
1&
0(
b0001 *
#596000000
0!
0&
#597000000
1!
1&
#598000000
0!
0&
#599000000
1!
1#
1&
1(
#600000000
0!
0&
#601000000
1!
0"
0$
b0011 %
1&
0'
0)
b0011 *
#602000000
0!
0&
#603000000
1!
b0000 %
1&
b0000 *
#604000000
0!
0&
#605000000
1!
1"
0#
1$
1&
1'
0(
1)
#606000000
0!
0&
#607000000
1!
1#
1&
1(
#608000000
0!
0&
#609000000
1!
0#
b0001 %
1&
0(
b0001 *
#610000000
0!
0&
#611000000
1!
1#
1&
1(
#612000000
0!
0&
#613000000
1!
0$
b0011 %
1&
0)
b0011 *
#614000000
0!
0&
#615000000
1!
1$
b0110 %
1&
1)
b0110 *
#616000000
0!
0&
#617000000
1!
0#
b1101 %
1&
0(
b1101 *
#618000000
0!
0&
#619000000
1!
0"
0$
1&
0'
0)
#620000000
0!
0&
#621000000
1!
1"
1#
b0000 %
1&
1'
1(
b0000 *
#622000000
0!
0&
#623000000
1!
0#
1$
1&
0(
1)
#624000000
0!
0&
#625000000
1!
1#
0$
1&
1(
0)
#626000000
0!
0&
#627000000
1!
1$
1&
1)
#628000000
0!
0&
#629000000
1!
0#
b0001 %
1&
0(
b0001 *
#630000000
0!
0&
#631000000
1!
0$
1&
0)
#632000000
0!
0&
#633000000
1!
1&
#634000000
0!
0&
#635000000
1!
1&
#636000000
0!
0&
#637000000
1!
1$
1&
1)
#638000000
0!
0&
#639000000
1!
1&
#640000000
0!
0&
#641000000
1!
1#
0$
1&
1(
0)
#642000000
0!
0&
#643000000
1!
1$
b0010 %
1&
1)
b0010 *
#644000000
0!
0&
#645000000
1!
0#
b0101 %
1&
0(
b0101 *
#646000000
0!
0&
#647000000
1!
1&
#648000000
0!
0&
#649000000
1!
1#
0$
1&
1(
0)
#650000000
0!
0&
#651000000
1!
0#
b1010 %
1&
0(
b1010 *
#652000000
0!
0&
#653000000
1!
1$
1&
1)
#654000000
0!
0&
#655000000
1!
1#
1&
1(
#656000000
0!
0&
#657000000
1!
0#
0$
b0101 %
1&
0(
0)
b0101 *
#658000000
0!
0&
#659000000
1!
1$
1&
1)
#660000000
0!
0&
#661000000
1!
1#
1&
1(
#662000000
0!
0&
#663000000
1!
b1011 %
1&
b1011 *
#664000000
0!
0&
#665000000
1!
0#
0$
b0111 %
1&
0(
0)
b0111 *
#666000000
0!
0&
#667000000
1!
1&
#668000000
0!
0&
#669000000
1!
1#
1&
1(
#670000000
0!
0&
#671000000
1!
0#
1$
b1110 %
1&
0(
1)
b1110 *
#672000000
0!
0&
#673000000
1!
0$
1&
0)
#674000000
0!
0&
#675000000
1!
1&
#676000000
0!
0&
#677000000
1!
1$
1&
1)
#678000000
0!
0&
#679000000
1!
0"
1&
0'
#680000000
0!
0&
#681000000
1!
1"
0$
b0000 %
1&
1'
0)
b0000 *
#682000000
0!
0&
#683000000
1!
1&
#684000000
0!
0&
#685000000
1!
1#
1&
1(
#686000000
0!
0&
#687000000
1!
0#
1&
0(
#688000000
0!
0&
#689000000
1!
1#
1$
1&
1(
1)
#690000000
0!
0&
#691000000
1!
0#
b0001 %
1&
0(
b0001 *
#692000000
0!
0&
#693000000
1!
1#
1&
1(
#694000000
0!
0&
#695000000
1!
0#
b0011 %
1&
0(
b0011 *
#696000000
0!
0&
#697000000
1!
1#
0$
1&
1(
0)
#698000000
0!
0&
#699000000
1!
0"
0#
1$
b0110 %
1&
0'
0(
1)
b0110 *
#700000000
0!
0&
#701000000
1!
1"
1#
0$
b0000 %
1&
1'
1(
0)
b0000 *
#702000000
0!
0&
#703000000
1!
1&
#704000000
0!
0&
#705000000
1!
0#
1&
0(
#706000000
0!
0&
#707000000
1!
1&
#708000000
0!
0&
#709000000
1!
1&
#710000000
0!
0&
#711000000
1!
1$
1&
1)
#712000000
0!
0&
#713000000
1!
0$
1&
0)
#714000000
0!
0&
#715000000
1!
1&
#716000000
0!
0&
#717000000
1!
1&
#718000000
0!
0&
#719000000
1!
1#
1$
1&
1(
1)
#720000000
0!
0&
#721000000
1!
0$
b0001 %
1&
0)
b0001 *
#722000000
0!
0&
#723000000
1!
b0010 %
1&
b0010 *
#724000000
0!
0&
#725000000
1!
0#
b0100 %
1&
0(
b0100 *
#726000000
0!
0&
#727000000
1!
1&
#728000000
0!
0&
#729000000
1!
1&
#730000000
0!
0&
#731000000
1!
1#
1&
1(
#732000000
0!
0&
#733000000
1!
0#
b1000 %
1&
0(
b1000 *
#734000000
0!
0&
#735000000
1!
1$
1&
1)
#736000000
0!
0&
#737000000
1!
0"
1#
0$
1&
0'
1(
0)
#738000000
0!
0&
#739000000
1!
1"
0#
b0000 %
1&
1'
0(
b0000 *
#740000000
0!
0&
#741000000
1!
1#
1&
1(
#742000000
0!
0&
#743000000
1!
0#
1$
1&
0(
1)
#744000000
0!
0&
#745000000
1!
0"
1&
0'
#746000000
0!
0&
#747000000
1!
1"
1&
1'
#748000000
0!
0&
#749000000
1!
1#
0$
1&
1(
0)
#750000000
0!
0&
#751000000
1!
1&
#752000000
0!
0&
#753000000
1!
0"
1$
1&
0'
1)
#754000000
0!
0&
#755000000
1!
1"
1&
1'
#756000000
0!
0&
#757000000
1!
0#
0$
b0001 %
1&
0(
0)
b0001 *
#758000000
0!
0&
#759000000
1!
1&
#760000000
0!
0&
#761000000
1!
1#
1&
1(
#762000000
0!
0&
#763000000
1!
b0010 %
1&
b0010 *
#764000000
0!
0&
#765000000
1!
0"
0#
1$
b0100 %
1&
0'
0(
1)
b0100 *
#766000000
0!
0&
#767000000
1!
1"
1#
b0000 %
1&
1'
1(
b0000 *
#768000000
0!
0&
#769000000
1!
b0001 %
1&
b0001 *
