vhdl/lab03/timer.vhd
library ieee;
use ieee.std_logic_1164.all;
use ieee.numeric_std_unsigned.all;

entity timer is
  generic(
    f_mhz : positive range 1 to 1000 := 100;
    max_us : natural := 10
  );
  port(
    clk : in std_ulogic;
    sresetn : in std_ulogic;
    tz : in std_ulogic;
    t : out natural range 0 to max_us
  );
end entity timer;

architecture rtl of timer is

  signal cnt : natural range 0 to f_mhz-1;

  begin
  process(clk)
  begin
    if rising_edge(clk) then
      if not sresetn then
        cnt <= 0;
      elsif tz then
        cnt <= 0;
      elsif t /= max_us then
        if cnt = f_mhz-1 then
          cnt <= 0;
        else
          cnt <= cnt + 1;
        end if;
      end if;
    end if;
  end process;

  process(clk)
  begin
    if rising_edge(clk) then
      if not sresetn then
        t <= 0;
      elsif tz then
        t <= 0;
      elsif t /= max_us then
        if cnt = f_mhz-1 then
          t <= t + 1;
        end if;
      end if;
    end if;
  end process;
end architecture rtl;

vhdl/lab03/timer_sim.vhd
-- MASTER-ONLY: DO NOT MODIFY THIS FILE
--
-- Copyright (C) Telecom Paris
-- Copyright (C) Renaud Pacalet (renaud.pacalet@telecom-paris.fr)
-- 
-- This file must be used under the terms of the CeCILL. This source
-- file is licensed as described in the file COPYING, which you should
-- have received as part of this distribution. The terms are also
-- available at:
-- http://www.cecill.info/licences/Licence_CeCILL_V1.1-US.txt
--

entity timer_sim is
    generic(
        d:      positive                 := 1000; -- duration of test in clock cycles
        f_mhz:  positive range 1 to 1000 := 2;
        max_us: natural                  := 3
    );
end entity timer_sim;

use std.env.all;

library ieee;
use ieee.std_logic_1164.all;

library common;
use common.rnd_pkg.all;

architecture sim of timer_sim is

    signal clk:      std_ulogic;
    signal sresetn:  std_ulogic;
    signal tz:       std_ulogic;
    signal t:        natural range 0 to max_us;

begin

    timer0: entity work.timer(rtl)
    generic map(
        f_mhz  => f_mhz,
        max_us => max_us
    )
    port map(
        clk     => clk,
        sresetn => sresetn,
        tz      => tz,
        t       => t
    );

    process
    begin
        clk <= '0';
        wait for 1 ns;
        clk <= '1';
        wait for 1 ns;
    end process;

    process
        variable r: rnd_generator;
    begin
        sresetn <= '0';
        tz      <= '0';
        for i in 1 to 10 loop
            wait until rising_edge(clk);
        end loop;
        sresetn <= '1';
        for i in 1 to d loop
            -- Reset with 1/10 probability
            if r.get_integer(1, 10) = 1 then
                sresetn <= '0';
            else
                sresetn <= '1';
            end if;
            -- Zero timer with 1/10 probability
            if r.get_integer(1, 10) = 1 then
                tz <= '1';
            else
                tz <= '0';
            end if;
            wait until rising_edge(clk);
        end loop;
        finish;
    end process;

end architecture sim;

-- vim: set tabstop=4 softtabstop=4 shiftwidth=4 expandtab textwidth=0:

sim/timer_sim.vcd
$date
  Tue Mar 15 14:40:16 2022
$end
$version
  GHDL v0
$end
$timescale
  1 fs
$end
$scope module standard $end
$upscope $end
$scope module env $end
$upscope $end
$scope module textio $end
$upscope $end
$scope module std_logic_1164 $end
$upscope $end
$scope module rnd_pkg $end
$upscope $end
$scope module math_real $end
$upscope $end
$scope module numeric_std_unsigned $end
$upscope $end
$scope module numeric_std $end
$upscope $end
$scope module timer_sim $end
$var reg 1 ! clk $end
$var reg 1 " sresetn $end
$var reg 1 # tz $end
$var integer 32 $ t $end
$scope module timer0 $end
$var reg 1 % clk $end
$var reg 1 & sresetn $end
$var reg 1 ' tz $end
$var integer 32 ( t $end
$var integer 32 ) cnt $end
$upscope $end
$upscope $end
$enddefinitions $end
#0
0!
0"
0#
b0 $
0%
0&
0'
b0 (
b0 )
#1000000
1!
1%
#2000000
0!
0%
#3000000
1!
1%
#4000000
0!
0%
#5000000
1!
1%
#6000000
0!
0%
#7000000
1!
1%
#8000000
0!
0%
#9000000
1!
1%
#10000000
0!
0%
#11000000
1!
1%
#12000000
0!
0%
#13000000
1!
1%
#14000000
0!
0%
#15000000
1!
1%
#16000000
0!
0%
#17000000
1!
1%
#18000000
0!
0%
#19000000
1!
1"
1%
1&
#20000000
0!
0%
#21000000
1!
1%
b1 )
#22000000
0!
0%
#23000000
1!
0"
b1 $
1%
0&
b1 (
b0 )
#24000000
0!
0%
#25000000
1!
1"
1#
b0 $
1%
1&
1'
b0 (
#26000000
0!
0%
#27000000
1!
0#
1%
0'
#28000000
0!
0%
#29000000
1!
1%
b1 )
#30000000
0!
0%
#31000000
1!
b1 $
1%
b1 (
b0 )
#32000000
0!
0%
#33000000
1!
1%
b1 )
#34000000
0!
0%
#35000000
1!
b10 $
1%
b10 (
b0 )
#36000000
0!
0%
#37000000
1!
0"
1%
0&
b1 )
#38000000
0!
0%
#39000000
1!
1"
b0 $
1%
1&
b0 (
b0 )
#40000000
0!
0%
#41000000
1!
1#
1%
1'
b1 )
#42000000
0!
0%
#43000000
1!
1%
b0 )
#44000000
0!
0%
#45000000
1!
0#
1%
0'
#46000000
0!
0%
#47000000
1!
1%
b1 )
#48000000
0!
0%
#49000000
1!
0"
b1 $
1%
0&
b1 (
b0 )
#50000000
0!
0%
#51000000
1!
1"
b0 $
1%
1&
b0 (
#52000000
0!
0%
#53000000
1!
0"
1%
0&
b1 )
#54000000
0!
0%
#55000000
1!
1"
1%
1&
b0 )
#56000000
0!
0%
#57000000
1!
1%
b1 )
#58000000
0!
0%
#59000000
1!
b1 $
1%
b1 (
b0 )
#60000000
0!
0%
#61000000
1!
0"
1%
0&
b1 )
#62000000
0!
0%
#63000000
1!
1"
b0 $
1%
1&
b0 (
b0 )
#64000000
0!
0%
#65000000
1!
1%
b1 )
#66000000
0!
0%
#67000000
1!
b1 $
1%
b1 (
b0 )
#68000000
0!
0%
#69000000
1!
1%
b1 )
#70000000
0!
0%
#71000000
1!
b10 $
1%
b10 (
b0 )
#72000000
0!
0%
#73000000
1!
1%
b1 )
#74000000
0!
0%
#75000000
1!
b11 $
1%
b11 (
b0 )
#76000000
0!
0%
#77000000
1!
1%
#78000000
0!
0%
#79000000
1!
1%
#80000000
0!
0%
#81000000
1!
1%
#82000000
0!
0%
#83000000
1!
1#
1%
1'
#84000000
0!
0%
#85000000
1!
0#
b0 $
1%
0'
b0 (
#86000000
0!
0%
#87000000
1!
1%
b1 )
#88000000
0!
0%
#89000000
1!
b1 $
1%
b1 (
b0 )
#90000000
0!
0%
#91000000
1!
1%
b1 )
#92000000
0!
0%
#93000000
1!
b10 $
1%
b10 (
b0 )
#94000000
0!
0%
#95000000
1!
1%
b1 )
#96000000
0!
0%
#97000000
1!
b11 $
1%
b11 (
b0 )
#98000000
0!
0%
#99000000
1!
1%
#100000000
0!
0%
#101000000
1!
1%
#102000000
0!
0%
#103000000
1!
1%
#104000000
0!
0%
#105000000
1!
1#
1%
1'
#106000000
0!
0%
#107000000
1!
0"
0#
b0 $
1%
0&
0'
b0 (
#108000000
0!
0%
#109000000
1!
1"
1%
1&
#110000000
0!
0%
#111000000
1!
1%
b1 )
#112000000
0!
0%
#113000000
1!
0"
b1 $
1%
0&
b1 (
b0 )
#114000000
0!
0%
#115000000
1!
1"
b0 $
1%
1&
b0 (
#116000000
0!
0%
#117000000
1!
1%
b1 )
#118000000
0!
0%
#119000000
1!
b1 $
1%
b1 (
b0 )
#120000000
0!
0%
#121000000
1!
1%
b1 )
#122000000
0!
0%
#123000000
1!
b10 $
1%
b10 (
b0 )
#124000000
0!
0%
#125000000
1!
0"
1%
0&
b1 )
#126000000
0!
0%
#127000000
1!
1"
1#
b0 $
1%
1&
1'
b0 (
b0 )
#128000000
0!
0%
#129000000
1!
0#
1%
0'
#130000000
0!
0%
#131000000
1!
1%
b1 )
#132000000
0!
0%
#133000000
1!
0"
b1 $
1%
0&
b1 (
b0 )
#134000000
0!
0%
#135000000
1!
1"
b0 $
1%
1&
b0 (
#136000000
0!
0%
#137000000
1!
1%
b1 )
#138000000
0!
0%
#139000000
1!
b1 $
1%
b1 (
b0 )
#140000000
0!
0%
#141000000
1!
1%
b1 )
#142000000
0!
0%
#143000000
1!
b10 $
1%
b10 (
b0 )
#144000000
0!
0%
#145000000
1!
1%
b1 )
#146000000
0!
0%
#147000000
1!
b11 $
1%
b11 (
b0 )
#148000000
0!
0%
#149000000
1!
1%
#150000000
0!
0%
#151000000
1!
1#
1%
1'
#152000000
0!
0%
#153000000
1!
0#
b0 $
1%
0'
b0 (
#154000000
0!
0%
#155000000
1!
1#
1%
1'
b1 )
#156000000
0!
0%
#157000000
1!
0#
1%
0'
b0 )
#158000000
0!
0%
#159000000
1!
0"
1%
0&
b1 )
#160000000
0!
0%
#161000000
1!
1%
b0 )
#162000000
0!
0%
#163000000
1!
1"
1%
1&
#164000000
0!
0%
#165000000
1!
1%
b1 )
#166000000
0!
0%
#167000000
1!
b1 $
1%
b1 (
b0 )
#168000000
0!
0%
#169000000
1!
1%
b1 )
#170000000
0!
0%
#171000000
1!
b10 $
1%
b10 (
b0 )
#172000000
0!
0%
#173000000
1!
0"
1#
1%
0&
1'
b1 )
#174000000
0!
0%
#175000000
1!
1"
0#
b0 $
1%
1&
0'
b0 (
b0 )
#176000000
0!
0%
#177000000
1!
1%
b1 )
#178000000
0!
0%
#179000000
1!
b1 $
1%
b1 (
b0 )
#180000000
0!
0%
#181000000
1!
1%
b1 )
#182000000
0!
0%
#183000000
1!
b10 $
1%
b10 (
b0 )
#184000000
0!
0%
#185000000
1!
1%
b1 )
#186000000
0!
0%
#187000000
1!
1#
b11 $
1%
1'
b11 (
b0 )
#188000000
0!
0%
#189000000
1!
0#
b0 $
1%
0'
b0 (
#190000000
0!
0%
#191000000
1!
1%
b1 )
#192000000
0!
0%
#193000000
1!
b1 $
1%
b1 (
b0 )
#194000000
0!
0%
#195000000
1!
1%
b1 )
#196000000
0!
0%
#197000000
1!
0"
b10 $
1%
0&
b10 (
b0 )
#198000000
0!
0%
#199000000
1!
b0 $
1%
b0 (
#200000000
0!
0%
#201000000
1!
1"
1%
1&
#202000000
0!
0%
#203000000
1!
1#
1%
1'
b1 )
#204000000
0!
0%
#205000000
1!
0#
1%
0'
b0 )
#206000000
0!
0%
#207000000
1!
1#
1%
1'
b1 )
#208000000
0!
0%
#209000000
1!
0#
1%
0'
b0 )
#210000000
0!
0%
#211000000
1!
1%
b1 )
#212000000
0!
0%
#213000000
1!
b1 $
1%
b1 (
b0 )
#214000000
0!
0%
#215000000
1!
1%
b1 )
#216000000
0!
0%
#217000000
1!
0"
b10 $
1%
0&
b10 (
b0 )
#218000000
0!
0%
#219000000
1!
1"
b0 $
1%
1&
b0 (
#220000000
0!
0%
#221000000
1!
1%
b1 )
#222000000
0!
0%
#223000000
1!
b1 $
1%
b1 (
b0 )
#224000000
0!
0%
#225000000
1!
1%
b1 )
#226000000
0!
0%
#227000000
1!
b10 $
1%
b10 (
b0 )
#228000000
0!
0%
#229000000
1!
1%
b1 )
#230000000
0!
0%
#231000000
1!
b11 $
1%
b11 (
b0 )
#232000000
0!
0%
#233000000
1!
1%
#234000000
0!
0%
#235000000
1!
1%
#236000000
0!
0%
#237000000
1!
1%
#238000000
0!
0%
#239000000
1!
1%
#240000000
0!
0%
#241000000
1!
1%
#242000000
0!
0%
#243000000
1!
1%
#244000000
0!
0%
#245000000
1!
1%
#246000000
0!
0%
#247000000
1!
1%
#248000000
0!
0%
#249000000
1!
1%
#250000000
0!
0%
#251000000
1!
1%
#252000000
0!
0%
#253000000
1!
1%
#254000000
0!
0%
#255000000
1!
1%
#256000000
0!
0%
#257000000
1!
1%
#258000000
0!
0%
#259000000
1!
0"
1%
0&
#260000000
0!
0%
#261000000
1!
1"
b0 $
1%
1&
b0 (
#262000000
0!
0%
#263000000
1!
1%
b1 )
#264000000
0!
0%
#265000000
1!
1#
b1 $
1%
1'
b1 (
b0 )
#266000000
0!
0%
#267000000
1!
0#
b0 $
1%
0'
b0 (
#268000000
0!
0%
#269000000
1!
1%
b1 )
#270000000
0!
0%
#271000000
1!
b1 $
1%
b1 (
b0 )
#272000000
0!
0%
#273000000
1!
1%
b1 )
#274000000
0!
0%
#275000000
1!
b10 $
1%
b10 (
b0 )
#276000000
0!
0%
#277000000
1!
1%
b1 )
#278000000
0!
0%
#279000000
1!
b11 $
1%
b11 (
b0 )
#280000000
0!
0%
#281000000
1!
1%
#282000000
0!
0%
#283000000
1!
1%
#284000000
0!
0%
#285000000
1!
1%
#286000000
0!
0%
#287000000
1!
1%
#288000000
0!
0%
#289000000
1!
0"
1%
0&
#290000000
0!
0%
#291000000
1!
1"
b0 $
1%
1&
b0 (
#292000000
0!
0%
#293000000
1!
1%
b1 )
#294000000
0!
0%
#295000000
1!
b1 $
1%
b1 (
b0 )
#296000000
0!
0%
#297000000
1!
0"
1%
0&
b1 )
#298000000
0!
0%
#299000000
1!
1"
b0 $
1%
1&
b0 (
b0 )
#300000000
0!
0%
#301000000
1!
0"
1%
0&
b1 )
#302000000
0!
0%
#303000000
1!
1"
1%
1&
b0 )
#304000000
0!
0%
#305000000
1!
0"
1%
0&
b1 )
#306000000
0!
0%
#307000000
1!
1"
1%
1&
b0 )
#308000000
0!
0%
#309000000
1!
0"
1%
0&
b1 )
#310000000
0!
0%
#311000000
1!
1"
1%
1&
b0 )
#312000000
0!
0%
#313000000
1!
1%
b1 )
#314000000
0!
0%
#315000000
1!
b1 $
1%
b1 (
b0 )
#316000000
0!
0%
#317000000
1!
1%
b1 )
#318000000
0!
0%
#319000000
1!
0"
1#
b10 $
1%
0&
1'
b10 (
b0 )
#320000000
0!
0%
#321000000
1!
1"
0#
b0 $
1%
1&
0'
b0 (
#322000000
0!
0%
#323000000
1!
1%
b1 )
#324000000
0!
0%
#325000000
1!
b1 $
1%
b1 (
b0 )
#326000000
0!
0%
#327000000
1!
1%
b1 )
#328000000
0!
0%
#329000000
1!
b10 $
1%
b10 (
b0 )
#330000000
0!
0%
#331000000
1!
1%
b1 )
#332000000
0!
0%
#333000000
1!
b11 $
1%
b11 (
b0 )
#334000000
0!
0%
#335000000
1!
1%
#336000000
0!
0%
#337000000
1!
1%
#338000000
0!
0%
#339000000
1!
1%
#340000000
0!
0%
#341000000
1!
1%
#342000000
0!
0%
#343000000
1!
1%
#344000000
0!
0%
#345000000
1!
1%
#346000000
0!
0%
#347000000
1!
1%
#348000000
0!
0%
#349000000
1!
1#
1%
1'
#350000000
0!
0%
#351000000
1!
0#
b0 $
1%
0'
b0 (
#352000000
0!
0%
#353000000
1!
1%
b1 )
#354000000
0!
0%
#355000000
1!
b1 $
1%
b1 (
b0 )
#356000000
0!
0%
#357000000
1!
1%
b1 )
#358000000
0!
0%
#359000000
1!
b10 $
1%
b10 (
b0 )
#360000000
0!
0%
#361000000
1!
1%
b1 )
#362000000
0!
0%
#363000000
1!
b11 $
1%
b11 (
b0 )
#364000000
0!
0%
#365000000
1!
1%
#366000000
0!
0%
#367000000
1!
1%
#368000000
0!
0%
#369000000
1!
0"
1%
0&
#370000000
0!
0%
#371000000
1!
1"
1#
b0 $
1%
1&
1'
b0 (
#372000000
0!
0%
#373000000
1!
0#
1%
0'
#374000000
0!
0%
#375000000
1!
1%
b1 )
#376000000
0!
0%
#377000000
1!
1#
b1 $
1%
1'
b1 (
b0 )
#378000000
0!
0%
#379000000
1!
0#
b0 $
1%
0'
b0 (
#380000000
0!
0%
#381000000
1!
1%
b1 )
#382000000
0!
0%
#383000000
1!
b1 $
1%
b1 (
b0 )
#384000000
0!
0%
#385000000
1!
0"
1%
0&
b1 )
#386000000
0!
0%
#387000000
1!
1"
b0 $
1%
1&
b0 (
b0 )
#388000000
0!
0%
#389000000
1!
1%
b1 )
#390000000
0!
0%
#391000000
1!
0"
b1 $
1%
0&
b1 (
b0 )
#392000000
0!
0%
#393000000
1!
1"
b0 $
1%
1&
b0 (
#394000000
0!
0%
#395000000
1!
1%
b1 )
#396000000
0!
0%
#397000000
1!
b1 $
1%
b1 (
b0 )
#398000000
0!
0%
#399000000
1!
1%
b1 )
#400000000
0!
0%
#401000000
1!
1#
b10 $
1%
1'
b10 (
b0 )
#402000000
0!
0%
#403000000
1!
0#
b0 $
1%
0'
b0 (
#404000000
0!
0%
#405000000
1!
1%
b1 )
#406000000
0!
0%
#407000000
1!
b1 $
1%
b1 (
b0 )
#408000000
0!
0%
#409000000
1!
1%
b1 )
#410000000
0!
0%
#411000000
1!
b10 $
1%
b10 (
b0 )
#412000000
0!
0%
#413000000
1!
1%
b1 )
#414000000
0!
0%
#415000000
1!
b11 $
1%
b11 (
b0 )
#416000000
0!
0%
#417000000
1!
1%
#418000000
0!
0%
#419000000
1!
1%
#420000000
0!
0%
#421000000
1!
1%
#422000000
0!
0%
#423000000
1!
1%
#424000000
0!
0%
#425000000
1!
1%
#426000000
0!
0%
#427000000
1!
1%
#428000000
0!
0%
#429000000
1!
1%
#430000000
0!
0%
#431000000
1!
1%
#432000000
0!
0%
#433000000
1!
1%
#434000000
0!
0%
#435000000
1!
1%
#436000000
0!
0%
#437000000
1!
1#
1%
1'
#438000000
0!
0%
#439000000
1!
0#
b0 $
1%
0'
b0 (
#440000000
0!
0%
#441000000
1!
0"
1%
0&
b1 )
#442000000
0!
0%
#443000000
1!
1"
1%
1&
b0 )
#444000000
0!
0%
#445000000
1!
1%
b1 )
#446000000
0!
0%
#447000000
1!
0"
b1 $
1%
0&
b1 (
b0 )
#448000000
0!
0%
#449000000
1!
1"
b0 $
1%
1&
b0 (
#450000000
0!
0%
#451000000
1!
1#
1%
1'
b1 )
#452000000
0!
0%
#453000000
1!
0#
1%
0'
b0 )
#454000000
0!
0%
#455000000
1!
1%
b1 )
#456000000
0!
0%
#457000000
1!
b1 $
1%
b1 (
b0 )
#458000000
0!
0%
#459000000
1!
1%
b1 )
#460000000
0!
0%
#461000000
1!
0"
b10 $
1%
0&
b10 (
b0 )
#462000000
0!
0%
#463000000
1!
1"
b0 $
1%
1&
b0 (
#464000000
0!
0%
#465000000
1!
0"
1%
0&
b1 )
#466000000
0!
0%
#467000000
1!
1"
1%
1&
b0 )
#468000000
0!
0%
#469000000
1!
1%
b1 )
#470000000
0!
0%
#471000000
1!
b1 $
1%
b1 (
b0 )
#472000000
0!
0%
#473000000
1!
1%
b1 )
#474000000
0!
0%
#475000000
1!
1#
b10 $
1%
1'
b10 (
b0 )
#476000000
0!
0%
#477000000
1!
b0 $
1%
b0 (
#478000000
0!
0%
#479000000
1!
0#
1%
0'
#480000000
0!
0%
#481000000
1!
1%
b1 )
#482000000
0!
0%
#483000000
1!
0"
b1 $
1%
0&
b1 (
b0 )
#484000000
0!
0%
#485000000
1!
1"
b0 $
1%
1&
b0 (
#486000000
0!
0%
#487000000
1!
1%
b1 )
#488000000
0!
0%
#489000000
1!
b1 $
1%
b1 (
b0 )
#490000000
0!
0%
#491000000
1!
1%
b1 )
#492000000
0!
0%
#493000000
1!
b10 $
1%
b10 (
b0 )
#494000000
0!
0%
#495000000
1!
0"
1%
0&
b1 )
#496000000
0!
0%
#497000000
1!
1"
b0 $
1%
1&
b0 (
b0 )
#498000000
0!
0%
#499000000
1!
0"
1%
0&
b1 )
#500000000
0!
0%
#501000000
1!
1"
1%
1&
b0 )
#502000000
0!
0%
#503000000
1!
0"
1%
0&
b1 )
#504000000
0!
0%
#505000000
1!
1"
1%
1&
b0 )
#506000000
0!
0%
#507000000
1!
1%
b1 )
#508000000
0!
0%
#509000000
1!
b1 $
1%
b1 (
b0 )
#510000000
0!
0%
#511000000
1!
1%
b1 )
#512000000
0!
0%
#513000000
1!
b10 $
1%
b10 (
b0 )
#514000000
0!
0%
#515000000
1!
1%
b1 )
#516000000
0!
0%
#517000000
1!
0"
b11 $
1%
0&
b11 (
b0 )
#518000000
0!
0%
#519000000
1!
1"
b0 $
1%
1&
b0 (
#520000000
0!
0%
#521000000
1!
1%
b1 )
#522000000
0!
0%
#523000000
1!
b1 $
1%
b1 (
b0 )
#524000000
0!
0%
#525000000
1!
1%
b1 )
#526000000
0!
0%
#527000000
1!
b10 $
1%
b10 (
b0 )
#528000000
0!
0%
#529000000
1!
1%
b1 )
#530000000
0!
0%
#531000000
1!
b11 $
1%
b11 (
b0 )
#532000000
0!
0%
#533000000
1!
1%
#534000000
0!
0%
#535000000
1!
0"
1#
1%
0&
1'
#536000000
0!
0%
#537000000
1!
1"
0#
b0 $
1%
1&
0'
b0 (
#538000000
0!
0%
#539000000
1!
0"
1%
0&
b1 )
#540000000
0!
0%
#541000000
1!
1"
1%
1&
b0 )
#542000000
0!
0%
#543000000
1!
1%
b1 )
#544000000
0!
0%
#545000000
1!
b1 $
1%
b1 (
b0 )
#546000000
0!
0%
#547000000
1!
1%
b1 )
#548000000
0!
0%
#549000000
1!
b10 $
1%
b10 (
b0 )
#550000000
0!
0%
#551000000
1!
1%
b1 )
#552000000
0!
0%
#553000000
1!
b11 $
1%
b11 (
b0 )
#554000000
0!
0%
#555000000
1!
1%
#556000000
0!
0%
#557000000
1!
1%
#558000000
0!
0%
#559000000
1!
0"
1%
0&
#560000000
0!
0%
#561000000
1!
1"
1#
b0 $
1%
1&
1'
b0 (
#562000000
0!
0%
#563000000
1!
0#
1%
0'
#564000000
0!
0%
#565000000
1!
1%
b1 )
#566000000
0!
0%
#567000000
1!
b1 $
1%
b1 (
b0 )
#568000000
0!
0%
#569000000
1!
1%
b1 )
#570000000
0!
0%
#571000000
1!
1#
b10 $
1%
1'
b10 (
b0 )
#572000000
0!
0%
#573000000
1!
0#
b0 $
1%
0'
b0 (
#574000000
0!
0%
#575000000
1!
1#
1%
1'
b1 )
#576000000
0!
0%
#577000000
1!
0#
1%
0'
b0 )
#578000000
0!
0%
#579000000
1!
1%
b1 )
#580000000
0!
0%
#581000000
1!
1#
b1 $
1%
1'
b1 (
b0 )
#582000000
0!
0%
#583000000
1!
0#
b0 $
1%
0'
b0 (
#584000000
0!
0%
#585000000
1!
1%
b1 )
#586000000
0!
0%
#587000000
1!
b1 $
1%
b1 (
b0 )
#588000000
0!
0%
#589000000
1!
1#
1%
1'
b1 )
#590000000
0!
0%
#591000000
1!
0#
b0 $
1%
0'
b0 (
b0 )
#592000000
0!
0%
#593000000
1!
1%
b1 )
#594000000
0!
0%
#595000000
1!
b1 $
1%
b1 (
b0 )
#596000000
0!
0%
#597000000
1!
1%
b1 )
#598000000
0!
0%
#599000000
1!
b10 $
1%
b10 (
b0 )
#600000000
0!
0%
#601000000
1!
1%
b1 )
#602000000
0!
0%
#603000000
1!
b11 $
1%
b11 (
b0 )
#604000000
0!
0%
#605000000
1!
1%
#606000000
0!
0%
#607000000
1!
1%
#608000000
0!
0%
#609000000
1!
1%
#610000000
0!
0%
#611000000
1!
1%
#612000000
0!
0%
#613000000
1!
1%
#614000000
0!
0%
#615000000
1!
1%
#616000000
0!
0%
#617000000
1!
1%
#618000000
0!
0%
#619000000
1!
1%
#620000000
0!
0%
#621000000
1!
0"
1%
0&
#622000000
0!
0%
#623000000
1!
1"
b0 $
1%
1&
b0 (
#624000000
0!
0%
#625000000
1!
0"
1%
0&
b1 )
#626000000
0!
0%
#627000000
1!
1"
1%
1&
b0 )
#628000000
0!
0%
#629000000
1!
1%
b1 )
#630000000
0!
0%
#631000000
1!
b1 $
1%
b1 (
b0 )
#632000000
0!
0%
#633000000
1!
1%
b1 )
#634000000
0!
0%
#635000000
1!
b10 $
1%
b10 (
b0 )
#636000000
0!
0%
#637000000
1!
1%
b1 )
#638000000
0!
0%
#639000000
1!
0"
b11 $
1%
0&
b11 (
b0 )
#640000000
0!
0%
#641000000
1!
1"
b0 $
1%
1&
b0 (
#642000000
0!
0%
#643000000
1!
0"
1#
1%
0&
1'
b1 )
#644000000
0!
0%
#645000000
1!
1"
0#
1%
1&
0'
b0 )
#646000000
0!
0%
#647000000
1!
1%
b1 )
#648000000
0!
0%
#649000000
1!
b1 $
1%
b1 (
b0 )
#650000000
0!
0%
#651000000
1!
1%
b1 )
#652000000
0!
0%
#653000000
1!
b10 $
1%
b10 (
b0 )
#654000000
0!
0%
#655000000
1!
1%
b1 )
#656000000
0!
0%
#657000000
1!
b11 $
1%
b11 (
b0 )
#658000000
0!
0%
#659000000
1!
1%
#660000000
0!
0%
#661000000
1!
0"
1%
0&
#662000000
0!
0%
#663000000
1!
1"
1#
b0 $
1%
1&
1'
b0 (
#664000000
0!
0%
#665000000
1!
0#
1%
0'
#666000000
0!
0%
#667000000
1!
1%
b1 )
#668000000
0!
0%
#669000000
1!
b1 $
1%
b1 (
b0 )
#670000000
0!
0%
#671000000
1!
1%
b1 )
#672000000
0!
0%
#673000000
1!
b10 $
1%
b10 (
b0 )
#674000000
0!
0%
#675000000
1!
1%
b1 )
#676000000
0!
0%
#677000000
1!
b11 $
1%
b11 (
b0 )
#678000000
0!
0%
#679000000
1!
1#
1%
1'
#680000000
0!
0%
#681000000
1!
0#
b0 $
1%
0'
b0 (
#682000000
0!
0%
#683000000
1!
1%
b1 )
#684000000
0!
0%
#685000000
1!
b1 $
1%
b1 (
b0 )
#686000000
0!
0%
#687000000
1!
1%
b1 )
#688000000
0!
0%
#689000000
1!
b10 $
1%
b10 (
b0 )
#690000000
0!
0%
#691000000
1!
1%
b1 )
#692000000
0!
0%
#693000000
1!
0"
b11 $
1%
0&
b11 (
b0 )
#694000000
0!
0%
#695000000
1!
b0 $
1%
b0 (
#696000000
0!
0%
#697000000
1!
1"
1%
1&
#698000000
0!
0%
#699000000
1!
0"
1%
0&
b1 )
#700000000
0!
0%
#701000000
1!
1"
1%
1&
b0 )
#702000000
0!
0%
#703000000
1!
1%
b1 )
#704000000
0!
0%
#705000000
1!
1#
b1 $
1%
1'
b1 (
b0 )
#706000000
0!
0%
#707000000
1!
0#
b0 $
1%
0'
b0 (
#708000000
0!
0%
#709000000
1!
1%
b1 )
#710000000
0!
0%
#711000000
1!
b1 $
1%
b1 (
b0 )
#712000000
0!
0%
#713000000
1!
1%
b1 )
#714000000
0!
0%
#715000000
1!
b10 $
1%
b10 (
b0 )
#716000000
0!
0%
#717000000
1!
1%
b1 )
#718000000
0!
0%
#719000000
1!
b11 $
1%
b11 (
b0 )
#720000000
0!
0%
#721000000
1!
1%
#722000000
0!
0%
#723000000
1!
1%
#724000000
0!
0%
#725000000
1!
1%
#726000000
0!
0%
#727000000
1!
1%
#728000000
0!
0%
#729000000
1!
1%
#730000000
0!
0%
#731000000
1!
1%
#732000000
0!
0%
#733000000
1!
0"
1%
0&
#734000000
0!
0%
#735000000
1!
1"
b0 $
1%
1&
b0 (
#736000000
0!
0%
#737000000
1!
1#
1%
1'
b1 )
#738000000
0!
0%
#739000000
1!
0#
1%
0'
b0 )
#740000000
0!
0%
#741000000
1!
1%
b1 )
#742000000
0!
0%
#743000000
1!
b1 $
1%
b1 (
b0 )
#744000000
0!
0%
#745000000
1!
1%
b1 )
#746000000
0!
0%
#747000000
1!
b10 $
1%
b10 (
b0 )
#748000000
0!
0%
#749000000
1!
1%
b1 )
#750000000
0!
0%
#751000000
1!
b11 $
1%
b11 (
b0 )
#752000000
0!
0%
#753000000
1!
1%
#754000000
0!
0%
#755000000
1!
1%
#756000000
0!
0%
#757000000
1!
1%
#758000000
0!
0%
#759000000
1!
1#
1%
1'
#760000000
0!
0%
#761000000
1!
0#
b0 $
1%
0'
b0 (
#762000000
0!
0%
#763000000
1!
1%
b1 )
#764000000
0!
0%
#765000000
1!
b1 $
1%
b1 (
b0 )
#766000000
0!
0%
#767000000
1!
1#
1%
1'
b1 )
#768000000
0!
0%
#769000000
1!
0#
b0 $
1%
0'
b0 (
b0 )
#770000000
0!
0%
#771000000
1!
1%
b1 )
#772000000
0!
0%
#773000000
1!
1#
b1 $
1%
1'
b1 (
b0 )
#774000000
0!
0%
#775000000
1!
0"
0#
b0 $
1%
0&
0'
b0 (
#776000000
0!
0%
#777000000
1!
1"
1%
1&
#778000000
0!
0%
#779000000
1!
1%
b1 )
#780000000
0!
0%
#781000000
1!
b1 $
1%
b1 (
b0 )
#782000000
0!
0%
#783000000
1!
1%
b1 )
#784000000
0!
0%
#785000000
1!
0"
b10 $
1%
0&
b10 (
b0 )
#786000000
0!
0%
#787000000
1!
1"
1#
b0 $
1%
1&
1'
b0 (
#788000000
0!
0%
#789000000
1!
0#
1%
0'
#790000000
0!
0%
#791000000
1!
1%
b1 )
#792000000
0!
0%
#793000000
1!
0"
b1 $
1%
0&
b1 (
b0 )
#794000000
0!
0%
#795000000
1!
1"
b0 $
1%
1&
b0 (
#796000000
0!
0%
#797000000
1!
1%
b1 )
#798000000
0!
0%
#799000000
1!
b1 $
1%
b1 (
b0 )
#800000000
0!
0%
#801000000
1!
1#
1%
1'
b1 )
#802000000
0!
0%
#803000000
1!
0#
b0 $
1%
0'
b0 (
b0 )
#804000000
0!
0%
#805000000
1!
1%
b1 )
#806000000
0!
0%
#807000000
1!
b1 $
1%
b1 (
b0 )
#808000000
0!
0%
#809000000
1!
1#
1%
1'
b1 )
#810000000
0!
0%
#811000000
1!
0#
b0 $
1%
0'
b0 (
b0 )
#812000000
0!
0%
#813000000
1!
1%
b1 )
#814000000
0!
0%
#815000000
1!
b1 $
1%
b1 (
b0 )
#816000000
0!
0%
#817000000
1!
1%
b1 )
#818000000
0!
0%
#819000000
1!
b10 $
1%
b10 (
b0 )
#820000000
0!
0%
#821000000
1!
1%
b1 )
#822000000
0!
0%
#823000000
1!
0"
b11 $
1%
0&
b11 (
b0 )
#824000000
0!
0%
#825000000
1!
1"
b0 $
1%
1&
b0 (
#826000000
0!
0%
#827000000
1!
1%
b1 )
#828000000
0!
0%
#829000000
1!
b1 $
1%
b1 (
b0 )
#830000000
0!
0%
#831000000
1!
1%
b1 )
#832000000
0!
0%
#833000000
1!
0"
1#
b10 $
1%
0&
1'
b10 (
b0 )
#834000000
0!
0%
#835000000
1!
0#
b0 $
1%
0'
b0 (
#836000000
0!
0%
#837000000
1!
1"
1%
1&
#838000000
0!
0%
